Workbook
Name B.D: Tabla5[]
Name BD: Tabla5[]

Sheet B.D
B1: BASE DE DATOS
B3: CLIENTE | C3: NIT | F3: PROVEEDOR | G3: NIT
B4: ALGAMAR S.A | C4: 890.907.797-4 | F4: INDUSTRIAS JB S.A.S | G4: 890.923.680-0
B5: HPTU | C5: 890.901.826-2 | F5: LUZ MARINA PAMPLONA | G5: 42.765.696-1
B6: EFITRANS | C6: 811.028.194-4 | F6: ESPINTURAS S.A.S | G6: 900.113.676-9
B7: EL TESORO ENTRETENIMIENTO | C7: 900.534.009-2 | F7: PRODUCTOS COPLAST | G7: 890.928.831-7
B8: REIMPEX S.A | C8: 890.939.592-0 | F8: CENCOSUD COLOMBIA S.A | G8: 900.155.107-1
B9: URBANIZACION SAINT PIERRE P.H | C9: 900.730.853-0 | F9: COMERCIALIZADORA CALYPSO S.A.S | G9: 860.075.208-7
B10: URBANIZACION SAINT MARTEEN P.H | C10: 900.730.967-3 | F10: PC CHAMPION S.A.S | G10: 830.022.380-1
B11: HECKCACOL SERVICIOS INDUSTRIALES S.A.S | C11: 900.678.158-1 | F11: AREA TUNNING LUJOS Y SONIDOS S.A.S
B12: PLATAFORMA LOGISTICA Y COMERCIAL S.A.S | C12: 901.092.692-9 | F12: CENTRO DE SERVICIOS BELLO S.A.S. | G12: 811.000.785-5
B13: RISKS & PROTECTION LTDA | C13: 900.171.792-2 | F13: ANDRES FERNEY PUERTA | G13: 71.212.993-7
B14: CARLOS MARIO MOLINA V | C14: 98.640.058-9 | F14: FERROSVEL S.A.S | G14: 890.910.715-1
B15: EFITRANS S.A.S | C15: 811.028.194-4 | F15: SODIMAC COLOMBIA | G15: 800.242.106-2
B16: SINTRABANCOL | C16: 860.013.526-9 | F16: PRODUCTOS COPLAST | G16: 890.928.831-7
B17: FIJACIONES OROZCO S.A.S | C17: 900.378.955-6 | F17: JUAN F. ESTRADA | G17: 71.315.681-7
B18: GABRIEL ARTURO ALZATE | C18: 8.277.443-8 | F18: ALMACENES CORONA S.A.S | G18: 860.500.480-8
B19: CENTRO MEDICO VETERINARIO BELLOS CANES | C19: 901.061.785-2 | F19: MATERIALES SU CONSTRUCCION S.A | G19: 800.147.650-1
B20: INGENIERIA EFICIENTE DEL AIRE S.A.S | C20: 900.729.224-8 | F20: AUTOLATAS S.A.S | G20: 901.165.210-7
B21: ELEVEMOS S.A.S | C21: 900.790.148-4 | F21: MATERIALES EL TITAN 1 S.A.S | G21: 811.023.960-7
B22: PROELECTRA DE COLOMBIA S.A.S | C22: 900.531.259-3 | F22: J&J ASOCIADOS | G22: 811.047.183-4
B23: EL CHAQUIRO | C23: 811.130.040-3 | F23: ANDRES FERNEY PUERTA | G23: 71.212.993-7
B24: URBANIZACION ALTOS DEL POBLADO 1 P.H | F24: SOFIA POSADA S.A.S | G24: 901.099.232-6
B25: EDIFICIO GRAN MEDITERRANEO | C25: 800.200.948-7 | F25: COEXITO S.A.S | G25: 890.300.225-7
B26: TRANSPORTE Y TURISMO 1A S.A.S | C26: 811.010.604-3 | F26: CENTRAL DE AMORTIGUADORES
B27: CONJUNTO RESIDENCIAL PALOS DE MOGUER | C27: 890.938.162-0 | F27: PEDRO ANTONIO HERRERA | G27: 8.228.782-0
B28: IMPERIAL ELEVADORES S.A.S | C28: 900.828.771-1 | F28: PLASTEXTIL S.A.S | G28: 890.900.372-6
B29: URBANIZACION VILLAS DE SAN JOSE | C29: 800254196 | F29: TODO TAPICERO S.A | G29: 811.019.431-7
B30: FULL ZONE S.A.S | C30: 900.531.699-0 | F30: ALMACEN PLASTITELAS S.A | G30: 800.028.761-0
B31: EDIFICIO BASILEA | C31: 900.488.501-8 | F31: RELOMAR S.A.S | G31: 900.948.601-0
B32: C.R TORRES DEL CASTILLO | C32: 890.937.289-2 | F32: MA. ALEJANDRA TANGARIFE | G32: 1128422587-8
B33: EDIFICIO CHAPELET P.H | C33: 900.872.144-8 | F33: GHMC S.A.S | G33: 900.199.391-4
B34: URBANIZACION PENINSULA CONDOMINIO P.H | C34: 900.518.640-3 | F34: CENTRO ELECTRICO AT. E.U | G34: 811.013.030-1
B35: CONJUNTO MULTIFAMILIAR PRADO DE VILLANUEVA | C35: 811.046.856-8 | F35: COMERCIALIZADORA GIRALDO Z S.A.S | G35: 900.838.480-9
B36: EDIFICIO SHINGALE P.H | C36: 800.253.169-3 | F36: LUZ PIEDAD ESPINOSA | G36: 21.395.737-0
B37: CENTRO COMERCIAL LOS MARINILLOS PH | C37: 900.294.051-1 | F37: ALMACEN RAMO ELECTRICOS S.A.S | G37: 800.175.064-4
B38: ELEVADORES TECNIVEC S.A.S | C38: 901.238.336-0 | F38: GUILLERMO LEON BEDOYA | G38: 71.396.968-1
B39: AMERICANA DE ELEVADORES | C39: 900.313.705-2 | F39: FORMATEX LA 50 | G39: 900.025.648-5
B40: EDIFICIO CATANIA | C40: 811.020.023-7 | F40: FIJACIONES OROZCO S.A.S | G40: 900.378.955-6
B41: TRANSPORTES ESPECIALES A&S S.A.S | C41: 900.549.783-0 | F41: SERVITECA LUBRIFILTROS BELLO S.A.S | G41: 900.704.790-7
B42: OMC INGENIERIA S.A.S | C42: 901.412.993-5 | F42: CONQUILLANTAS | G42: 71.773,073-2

Sheet VENTAS
L1: =+SUM(CLIENTE[slado]) -> 5315000.4
A2: FECHA | B2: MES | C2: AÑO | D2: DOCUMENTO | E2: CLIENTE | F2: NIT | G2: VALOR | H2: RTE FTE | I2: V. NETO | J2: DESCRIPCION | K2: Abono | L2: slado | M2: Columna1 | N2: Columna2
A3: 43115 | B3: =TEXT(CLIENTE[[#This Row],[FECHA]],"MMMM") -> enero | C3: =TEXT(CLIENTE[[#This Row],[FECHA]],"YYYY") -> 2018 | D3: 48 | E3: ALGAMAR S.A | F3: =VLOOKUP(CLIENTE[[#This Row],[CLIENTE]],Tabla5[],2,FALSE) -> 890.907.797-4 | G3: 8470000 | H3: =+G3*3.5% -> 296450 | I3: =+G3-H3 -> 8173550 | J3: 14 SOMBRILLAS 1.8X1.8 LONA HURACAN | K3: 8173550 | L3: =+CLIENTE[[#This Row],[VALOR]]-CLIENTE[[#This Row],[RTE FTE]]-CLIENTE[[#This Row],[Abono]] -> 0
A4: 43122 | B4: =TEXT(CLIENTE[[#This Row],[FECHA]],"MMMM") -> enero | C4: =TEXT(CLIENTE[[#This Row],[FECHA]],"YYYY") -> 2018 | D4: 49 | E4: HPTU | F4: =VLOOKUP(CLIENTE[[#This Row],[CLIENTE]],Tabla5[],2,FALSE) -> 890.901.826-2 | G4: 810000 | H4: 0 | I4: =+G4+H4 -> 810000 | J4: ALQUILER DE CARPA Y CORTINAS 3 CAMPAÑAS | K4: 810000 | L4: =+CLIENTE[[#This Row],[VALOR]]-CLIENTE[[#This Row],[RTE FTE]]-CLIENTE[[#This Row],[Abono]] -> 0
A5: 43126 | B5: =TEXT(CLIENTE[[#This Row],[FECHA]],"MMMM") -> enero | C5: =TEXT(CLIENTE[[#This Row],[FECHA]],"YYYY") -> 2018 | D5: 50 | E5: EFITRANS | F5: =VLOOKUP(CLIENTE[[#This Row],[CLIENTE]],Tabla5[],2,FALSE) -> 811.028.194-4 | G5: 380000 | H5: 0 | I5: =+G5+H5 -> 380000 | J5: SOMBRILLA EN MADERA | K5: 380000 | L5: =+CLIENTE[[#This Row],[VALOR]]-CLIENTE[[#This Row],[RTE FTE]]-CLIENTE[[#This Row],[Abono]] -> 0
A6: 43126 | B6: =TEXT(CLIENTE[[#This Row],[FECHA]],"MMMM") -> enero | C6: =TEXT(CLIENTE[[#This Row],[FECHA]],"YYYY") -> 2018 | D6: 51 | E6: EL TESORO ENTRETENIMIENTO | F6: =VLOOKUP(CLIENTE[[#This Row],[CLIENTE]],Tabla5[],2,FALSE) -> 900.534.009-2 | G6: 403560 | H6: =+G6*6% -> 24213.6 | I6: =+G6-H6 -> 379346.4 | J6: REPARACION DE 7 BALONES Y TRANSPORTE | K6: 379346 | L6: =+CLIENTE[[#This Row],[VALOR]]-CLIENTE[[#This Row],[RTE FTE]]-CLIENTE[[#This Row],[Abono]] -> 0.4
A7: 43136 | B7: =TEXT(CLIENTE[[#This Row],[FECHA]],"MMMM") -> febrero | C7: =TEXT(CLIENTE[[#This Row],[FECHA]],"YYYY") -> 2018 | D7: 52 | E7: ALGAMAR S.A | F7: =VLOOKUP(CLIENTE[[#This Row],[CLIENTE]],Tabla5[],2,FALSE) -> 890.907.797-4 | G7: 10890000 | H7: =+G7*3.5% -> 381150 | I7: =+G7-H7 -> 10508850 | J7: 18 SOMBRILLAS 1.8X1.8 LONA HURACAN | K7: 10508850 | L7: =+CLIENTE[[#This Row],[VALOR]]-CLIENTE[[#This Row],[RTE FTE]]-CLIENTE[[#This Row],[Abono]] -> 0
A8: 43138 | B8: =TEXT(CLIENTE[[#This Row],[FECHA]],"MMMM") -> febrero | C8: =TEXT(CLIENTE[[#This Row],[FECHA]],"YYYY") -> 2018 | D8: 53 | E8: EL TESORO ENTRETENIMIENTO | F8: =VLOOKUP(CLIENTE[[#This Row],[CLIENTE]],Tabla5[],2,FALSE) -> 900.534.009-2 | G8: 455800 | H8: =+G8*6% -> 27348 | I8: =+G8-H8 -> 428452 | J8: REPARACION DE 8 BALONES Y TRANSPORTE | K8: 428452 | L8: =+CLIENTE[[#This Row],[VALOR]]-CLIENTE[[#This Row],[RTE FTE]]-CLIENTE[[#This Row],[Abono]] -> 0
A9: 43139 | B9: =TEXT(CLIENTE[[#This Row],[FECHA]],"MMMM") -> febrero | C9: =TEXT(CLIENTE[[#This Row],[FECHA]],"YYYY") -> 2018 | D9: 54 | E9: REIMPEX S.A | F9: =VLOOKUP(CLIENTE[[#This Row],[CLIENTE]],Tabla5[],2,FALSE) -> 890.939.592-0 | G9: 370000 | H9: =+G9*4% -> 14800 | I9: =+G9-H9 -> 355200 | J9: ELECTRODOS-LONA Y MALLA-INDUCCION | K9: 355200 | L9: =+CLIENTE[[#This Row],[VALOR]]-CLIENTE[[#This Row],[RTE FTE]]-CLIENTE[[#This Row],[Abono]] -> 0
A10: 43152 | B10: =TEXT(CLIENTE[[#This Row],[FECHA]],"MMMM") -> febrero | C10: =TEXT(CLIENTE[[#This Row],[FECHA]],"YYYY") -> 2018 | D10: 57 | E10: URBANIZACION SAINT PIERRE P.H | F10: =VLOOKUP(CLIENTE[[#This Row],[CLIENTE]],Tabla5[],2,FALSE) -> 900.730.853-0 | G10: 367200 | H10: 0 | I10: =+G10-H10 -> 367200 | J10: LONA TERMICA PROTECTORA | K10: 367200 | L10: =+CLIENTE[[#This Row],[VALOR]]-CLIENTE[[#This Row],[RTE FTE]]-CLIENTE[[#This Row],[Abono]] -> 0
A11: 43152 | B11: =TEXT(CLIENTE[[#This Row],[FECHA]],"MMMM") -> febrero | C11: =TEXT(CLIENTE[[#This Row],[FECHA]],"YYYY") -> 2018 | D11: 58 | E11: URBANIZACION SAINT MARTEEN P.H | F11: =VLOOKUP(CLIENTE[[#This Row],[CLIENTE]],Tabla5[],2,FALSE) -> 900.730.967-3 | G11: 350000 | H11: =+G11*19% -> 66500 | I11: =+G11-H11 -> 283500 | J11: LONA PROTECTOR DE SOMBRILLA-LONA ARENERO | K11: 283500 | L11: =+CLIENTE[[#This Row],[VALOR]]-CLIENTE[[#This Row],[RTE FTE]]-CLIENTE[[#This Row],[Abono]] -> 0
A12: 43154 | B12: =TEXT(CLIENTE[[#This Row],[FECHA]],"MMMM") -> febrero | C12: =TEXT(CLIENTE[[#This Row],[FECHA]],"YYYY") -> 2018 | D12: 59 | E12: EL TESORO ENTRETENIMIENTO | F12: =VLOOKUP(CLIENTE[[#This Row],[CLIENTE]],Tabla5[],2,FALSE) -> 900.534.009-2 | G12: 560000 | H12: =+G12*6% -> 33600 | I12: =+G12-H12 -> 526400 | J12: REPARACION DE 10 BALONES Y TRANSPORTE | K12: 526400 | L12: =+CLIENTE[[#This Row],[VALOR]]-CLIENTE[[#This Row],[RTE FTE]]-CLIENTE[[#This Row],[Abono]] -> 0
A13: 43166 | B13: =TEXT(CLIENTE[[#This Row],[FECHA]],"MMMM") -> marzo | C13: =TEXT(CLIENTE[[#This Row],[FECHA]],"YYYY") -> 2018 | D13: 60 | E13: ALGAMAR S.A | F13: =VLOOKUP(CLIENTE[[#This Row],[CLIENTE]],Tabla5[],2,FALSE) -> 890.907.797-4 | G13: 3025000 | H13: =+G13*3.5% -> 105875 | I13: =+G13-H13 -> 2919125 | J13: 5 SOMBRILLAS 1.8X1.8 LONA HURACAN | K13: 2919125 | L13: =+CLIENTE[[#This Row],[VALOR]]-CLIENTE[[#This Row],[RTE FTE]]-CLIENTE[[#This Row],[Abono]] -> 0
A14: 43168 | B14: =TEXT(CLIENTE[[#This Row],[FECHA]],"MMMM") -> marzo | C14: =TEXT(CLIENTE[[#This Row],[FECHA]],"YYYY") -> 2018 | D14: 63 | E14: HECKCACOL SERVICIOS INDUSTRIALES S.A.S | F14: =VLOOKUP(CLIENTE[[#This Row],[CLIENTE]],Tabla5[],2,FALSE) -> 900.678.158-1 | G14: 650000 | H14: 0 | I14: =+G14-H14 -> 650000 | J14: LONA PROTECTORA DE ASCENSOR | K14: 650000 | L14: =+CLIENTE[[#This Row],[VALOR]]-CLIENTE[[#This Row],[RTE FTE]]-CLIENTE[[#This Row],[Abono]] -> 0
A15: 43228 | B15: =TEXT(CLIENTE[[#This Row],[FECHA]],"MMMM") -> mayo | C15: =TEXT(CLIENTE[[#This Row],[FECHA]],"YYYY") -> 2018 | D15: 64 | E15: EL TESORO ENTRETENIMIENTO | F15: =VLOOKUP(CLIENTE[[#This Row],[CLIENTE]],Tabla5[],2,FALSE) -> 900.534.009-2 | G15: 380000 | H15: 0 | I15: =+G15-H15 -> 380000 | J15: REPARACION DE 7 BALONES Y TRANSPORTE | K15: 380000 | L15: =+CLIENTE[[#This Row],[VALOR]]-CLIENTE[[#This Row],[RTE FTE]]-CLIENTE[[#This Row],[Abono]] -> 0
A16: 43237 | B16: =TEXT(CLIENTE[[#This Row],[FECHA]],"MMMM") -> mayo | C16: =TEXT(CLIENTE[[#This Row],[FECHA]],"YYYY") -> 2018 | D16: 65 | E16: EL TESORO ENTRETENIMIENTO | F16: =VLOOKUP(CLIENTE[[#This Row],[CLIENTE]],Tabla5[],2,FALSE) -> 900.534.009-2 | G16: 330000 | H16: 0 | I16: =+G16-H16 -> 330000 | J16: REPARACION DE 6 BALONES Y TRANSPORTE | K16: 330000 | L16: =+CLIENTE[[#This Row],[VALOR]]-CLIENTE[[#This Row],[RTE FTE]]-CLIENTE[[#This Row],[Abono]] -> 0
A17: 43238 | B17: =TEXT(CLIENTE[[#This Row],[FECHA]],"MMMM") -> mayo | C17: =TEXT(CLIENTE[[#This Row],[FECHA]],"YYYY") -> 2018 | D17: 66 | E17: PLATAFORMA LOGISTICA Y COMERCIAL S.A.S | F17: =VLOOKUP(CLIENTE[[#This Row],[CLIENTE]],Tabla5[],2,FALSE) -> 901.092.692-9 | G17: 1200000 | H17: =+G17*4% -> 48000 | I17: =+G17-H17 -> 1152000 | J17: ALQUILER DE LOCAL CRA 49#86-04 , MAYO 2018 | K17: 1152000 | L17: =+CLIENTE[[#This Row],[VALOR]]-CLIENTE[[#This Row],[RTE FTE]]-CLIENTE[[#This Row],[Abono]] -> 0
A18: 43238 | B18: =TEXT(CLIENTE[[#This Row],[FECHA]],"MMMM") -> mayo | C18: =TEXT(CLIENTE[[#This Row],[FECHA]],"YYYY") -> 2018 | D18: 67 | E18: PLATAFORMA LOGISTICA Y COMERCIAL S.A.S | F18: =VLOOKUP(CLIENTE[[#This Row],[CLIENTE]],Tabla5[],2,FALSE) -> 901.092.692-9 | G18: 1200000 | H18: =+G18*4% -> 48000 | I18: =+G18-H18 -> 1152000 | J18: ALQUILER DE LOCAL CRA 49#86-04 , JUNIO 2018 | K18: 1152000 | L18: =+CLIENTE[[#This Row],[VALOR]]-CLIENTE[[#This Row],[RTE FTE]]-CLIENTE[[#This Row],[Abono]] -> 0
A19: 43243 | B19: =TEXT(CLIENTE[[#This Row],[FECHA]],"MMMM") -> mayo | C19: =TEXT(CLIENTE[[#This Row],[FECHA]],"YYYY") -> 2018 | D19: 68 | E19: EL TESORO ENTRETENIMIENTO | F19: =VLOOKUP(CLIENTE[[#This Row],[CLIENTE]],Tabla5[],2,FALSE) -> 900.534.009-2 | G19: 230000 | H19: 0 | I19: =+G19-H19 -> 230000 | J19: REPARACION DE 4 BALONES Y TARSNPORTE | K19: 230000 | L19: =+CLIENTE[[#This Row],[VALOR]]-CLIENTE[[#This Row],[RTE FTE]]-CLIENTE[[#This Row],[Abono]] -> 0
A20: 43252 | B20: =TEXT(CLIENTE[[#This Row],[FECHA]],"MMMM") -> junio | C20: =TEXT(CLIENTE[[#This Row],[FECHA]],"YYYY") -> 2018 | D20: 69 | E20: EL TESORO ENTRETENIMIENTO | F20: =VLOOKUP(CLIENTE[[#This Row],[CLIENTE]],Tabla5[],2,FALSE) -> 900.534.009-2 | G20: 310000 | H20: 0 | I20: =+G20-H20 -> 310000 | J20: REPARION DE 5 BALONES Y TRASNPORTE | K20: 310000 | L20: =+CLIENTE[[#This Row],[VALOR]]-CLIENTE[[#This Row],[RTE FTE]]-CLIENTE[[#This Row],[Abono]] -> 0
A21: 43257 | B21: =TEXT(CLIENTE[[#This Row],[FECHA]],"MMMM") -> junio | C21: =TEXT(CLIENTE[[#This Row],[FECHA]],"YYYY") -> 2018 | D21: 70 | E21: EL TESORO ENTRETENIMIENTO | F21: =VLOOKUP(CLIENTE[[#This Row],[CLIENTE]],Tabla5[],2,FALSE) -> 900.534.009-2 | G21: 180000 | H21: 0 | I21: =+G21-H21 -> 180000 | J21: REPARACION DE 3 BALONES Y TRANSPORTE | K21: 180000 | L21: =+CLIENTE[[#This Row],[VALOR]]-CLIENTE[[#This Row],[RTE FTE]]-CLIENTE[[#This Row],[Abono]] -> 0
A22: 43259 | B22: =TEXT(CLIENTE[[#This Row],[FECHA]],"MMMM") -> junio | C22: =TEXT(CLIENTE[[#This Row],[FECHA]],"YYYY") -> 2018 | D22: 71 | E22: EL TESORO ENTRETENIMIENTO | F22: =VLOOKUP(CLIENTE[[#This Row],[CLIENTE]],Tabla5[],2,FALSE) -> 900.534.009-2 | G22: 430000 | H22: 0 | I22: =+G22-H22 -> 430000 | J22: REPARACION DE 8 BALONES Y TRANSPORTE | K22: 430000 | L22: =+CLIENTE[[#This Row],[VALOR]]-CLIENTE[[#This Row],[RTE FTE]]-CLIENTE[[#This Row],[Abono]] -> 0
A23: 43263 | B23: =TEXT(CLIENTE[[#This Row],[FECHA]],"MMMM") -> junio | C23: =TEXT(CLIENTE[[#This Row],[FECHA]],"YYYY") -> 2018 | D23: 72 | E23: EL TESORO ENTRETENIMIENTO | F23: =VLOOKUP(CLIENTE[[#This Row],[CLIENTE]],Tabla5[],2,FALSE) -> 900.534.009-2 | G23: 380000 | H23: 0 | I23: =+G23-H23 -> 380000 | J23: REPARACIONN DE 7 BALONES Y TRASNPORTE | K23: 380000 | L23: =+CLIENTE[[#This Row],[VALOR]]-CLIENTE[[#This Row],[RTE FTE]]-CLIENTE[[#This Row],[Abono]] -> 0
A24: 43265 | B24: =TEXT(CLIENTE[[#This Row],[FECHA]],"MMMM") -> junio | C24: =TEXT(CLIENTE[[#This Row],[FECHA]],"YYYY") -> 2018 | D24: 73 | E24: EL TESORO ENTRETENIMIENTO | F24: =VLOOKUP(CLIENTE[[#This Row],[CLIENTE]],Tabla5[],2,FALSE) -> 900.534.009-2 | G24: 480000 | H24: 0 | I24: =+G24-H24 -> 480000 | J24: REPARACION DE 9 BALONES Y TRASNPORTE | K24: 480000 | L24: =+CLIENTE[[#This Row],[VALOR]]-CLIENTE[[#This Row],[RTE FTE]]-CLIENTE[[#This Row],[Abono]] -> 0
A25: 43269 | B25: =TEXT(CLIENTE[[#This Row],[FECHA]],"MMMM") -> junio | C25: =TEXT(CLIENTE[[#This Row],[FECHA]],"YYYY") -> 2018 | D25: 74 | E25: ALGAMAR S.A | F25: =VLOOKUP(CLIENTE[[#This Row],[CLIENTE]],Tabla5[],2,FALSE) -> 890.907.797-4 | G25: 4235000 | H25: =+G25*3.5% -> 148225 | I25: =+G25-H25 -> 4086775 | J25: 7 SOMBRILLAS 1.8X1.8 | K25: 4086775 | L25: =+CLIENTE[[#This Row],[VALOR]]-CLIENTE[[#This Row],[RTE FTE]]-CLIENTE[[#This Row],[Abono]] -> 0
A26: 43271 | B26: =TEXT(CLIENTE[[#This Row],[FECHA]],"MMMM") -> junio | C26: =TEXT(CLIENTE[[#This Row],[FECHA]],"YYYY") -> 2018 | D26: 75 | E26: EL TESORO ENTRETENIMIENTO | F26: =VLOOKUP(CLIENTE[[#This Row],[CLIENTE]],Tabla5[],2,FALSE) -> 900.534.009-2 | G26: 130000 | H26: 0 | I26: =+G26-H26 -> 130000 | J26: REPARACION DE 2 BALONES Y TRASNPORTE | K26: 130000 | L26: =+CLIENTE[[#This Row],[VALOR]]-CLIENTE[[#This Row],[RTE FTE]]-CLIENTE[[#This Row],[Abono]] -> 0
A27: 43272 | B27: =TEXT(CLIENTE[[#This Row],[FECHA]],"MMMM") -> junio | C27: =TEXT(CLIENTE[[#This Row],[FECHA]],"YYYY") -> 2018 | D27: 76 | E27: RISKS & PROTECTION LTDA | F27: =VLOOKUP(CLIENTE[[#This Row],[CLIENTE]],Tabla5[],2,FALSE) -> 900.171.792-2 | G27: 350000 | H27: 0 | I27: =+G27-H27 -> 350000 | J27: FABRICACION DE LONA PARA SOMBRILLA | K27: 350000 | L27: =+CLIENTE[[#This Row],[VALOR]]-CLIENTE[[#This Row],[RTE FTE]]-CLIENTE[[#This Row],[Abono]] -> 0
A28: 43272 | B28: =TEXT(CLIENTE[[#This Row],[FECHA]],"MMMM") -> junio | C28: =TEXT(CLIENTE[[#This Row],[FECHA]],"YYYY") -> 2018 | D28: 77 | E28: EL TESORO ENTRETENIMIENTO | F28: =VLOOKUP(CLIENTE[[#This Row],[CLIENTE]],Tabla5[],2,FALSE) -> 900.534.009-2 | G28: 520000 | H28: 0 | I28: =+G28-H28 -> 520000 | J28: REPARACION DE 9 BALONES Y TRASNPORTE | K28: 520000 | L28: =+CLIENTE[[#This Row],[VALOR]]-CLIENTE[[#This Row],[RTE FTE]]-CLIENTE[[#This Row],[Abono]] -> 0
A29: 43278 | B29: =TEXT(CLIENTE[[#This Row],[FECHA]],"MMMM") -> junio | C29: =TEXT(CLIENTE[[#This Row],[FECHA]],"YYYY") -> 2018 | D29: 78 | E29: CARLOS MARIO MOLINA V | F29: =VLOOKUP(CLIENTE[[#This Row],[CLIENTE]],Tabla5[],2,FALSE) -> 98.640.058-9 | G29: 400000 | H29: 0 | I29: =+G29-H29 -> 400000 | J29: LONA PROTECTORA JACUZZI TORRE YINAN | K29: 400000 | L29: =+CLIENTE[[#This Row],[VALOR]]-CLIENTE[[#This Row],[RTE FTE]]-CLIENTE[[#This Row],[Abono]] -> 0
A30: 43278 | B30: =TEXT(CLIENTE[[#This Row],[FECHA]],"MMMM") -> junio | C30: =TEXT(CLIENTE[[#This Row],[FECHA]],"YYYY") -> 2018 | D30: 79 | E30: EL TESORO ENTRETENIMIENTO | F30: =VLOOKUP(CLIENTE[[#This Row],[CLIENTE]],Tabla5[],2,FALSE) -> 900.534.009-2 | G30: 800000 | H30: 0 | I30: =+G30-H30 -> 800000 | J30: REPARACION DE INFLABLE | K30: 800000 | L30: =+CLIENTE[[#This Row],[VALOR]]-CLIENTE[[#This Row],[RTE FTE]]-CLIENTE[[#This Row],[Abono]] -> 0
A31: 43278 | B31: =TEXT(CLIENTE[[#This Row],[FECHA]],"MMMM") -> junio | C31: =TEXT(CLIENTE[[#This Row],[FECHA]],"YYYY") -> 2018 | D31: 80 | E31: EL TESORO ENTRETENIMIENTO | F31: =VLOOKUP(CLIENTE[[#This Row],[CLIENTE]],Tabla5[],2,FALSE) -> 900.534.009-2 | G31: 410000 | H31: 0 | I31: =+G31-H31 -> 410000 | J31: REPARACION DE 7 BALONES Y TRANSPORTE | K31: 410000 | L31: =+CLIENTE[[#This Row],[VALOR]]-CLIENTE[[#This Row],[RTE FTE]]-CLIENTE[[#This Row],[Abono]] -> 0
A32: 43284 | B32: =TEXT(CLIENTE[[#This Row],[FECHA]],"MMMM") -> julio | C32: =TEXT(CLIENTE[[#This Row],[FECHA]],"YYYY") -> 2018 | D32: 81 | E32: PLATAFORMA LOGISTICA Y COMERCIAL S.A.S | F32: =VLOOKUP(CLIENTE[[#This Row],[CLIENTE]],Tabla5[],2,FALSE) -> 901.092.692-9 | G32: 1200000 | H32: =+G32*4% -> 48000 | I32: =+G32-H32 -> 1152000 | J32: ALQUILER DE LOCAL CRA 49#86-04 , JULIO 2018 | K32: 1152000 | L32: =+CLIENTE[[#This Row],[VALOR]]-CLIENTE[[#This Row],[RTE FTE]]-CLIENTE[[#This Row],[Abono]] -> 0
A33: 43285 | B33: =TEXT(CLIENTE[[#This Row],[FECHA]],"MMMM") -> julio | C33: =TEXT(CLIENTE[[#This Row],[FECHA]],"YYYY") -> 2018 | D33: 82 | E33: EL TESORO ENTRETENIMIENTO | F33: =VLOOKUP(CLIENTE[[#This Row],[CLIENTE]],Tabla5[],2,FALSE) -> 900.534.009-2 | G33: 580000 | H33: 0 | I33: =+G33-H33 -> 580000 | J33: REPARACION DE 11 BALONES Y TRASNPORTE | K33: 580000 | L33: =+CLIENTE[[#This Row],[VALOR]]-CLIENTE[[#This Row],[RTE FTE]]-CLIENTE[[#This Row],[Abono]] -> 0
A34: 43291 | B34: =TEXT(CLIENTE[[#This Row],[FECHA]],"MMMM") -> julio | C34: =TEXT(CLIENTE[[#This Row],[FECHA]],"YYYY") -> 2018 | D34: 83 | E34: EL TESORO ENTRETENIMIENTO | F34: =VLOOKUP(CLIENTE[[#This Row],[CLIENTE]],Tabla5[],2,FALSE) -> 900.534.009-2 | G34: 430000 | H34: 0 | I34: =+G34-H34 -> 430000 | J34: REPARACION DE 5 BALONES Y TRASNPORTE | K34: 430000 | L34: =+CLIENTE[[#This Row],[VALOR]]-CLIENTE[[#This Row],[RTE FTE]]-CLIENTE[[#This Row],[Abono]] -> 0
A35: 43292 | B35: =TEXT(CLIENTE[[#This Row],[FECHA]],"MMMM") -> julio | C35: =TEXT(CLIENTE[[#This Row],[FECHA]],"YYYY") -> 2018 | D35: 84 | E35: EL TESORO ENTRETENIMIENTO | F35: =VLOOKUP(CLIENTE[[#This Row],[CLIENTE]],Tabla5[],2,FALSE) -> 900.534.009-2 | G35: 430000 | H35: 0 | I35: =+G35-H35 -> 430000 | J35: REPARACION DE 8 BALONES Y TRANSPORTE | K35: 430000 | L35: =+CLIENTE[[#This Row],[VALOR]]-CLIENTE[[#This Row],[RTE FTE]]-CLIENTE[[#This Row],[Abono]] -> 0
A36: 43293 | B36: =TEXT(CLIENTE[[#This Row],[FECHA]],"MMMM") -> julio | C36: =TEXT(CLIENTE[[#This Row],[FECHA]],"YYYY") -> 2018 | D36: 85 | E36: EL TESORO ENTRETENIMIENTO | F36: =VLOOKUP(CLIENTE[[#This Row],[CLIENTE]],Tabla5[],2,FALSE) -> 900.534.009-2 | G36: 230000 | H36: 0 | I36: =+G36-H36 -> 230000 | J36: REPARACION DE 4 BALONES Y TARSNPORTE | K36: 230000 | L36: =+CLIENTE[[#This Row],[VALOR]]-CLIENTE[[#This Row],[RTE FTE]]-CLIENTE[[#This Row],[Abono]] -> 0
A37: 43300 | B37: =TEXT(CLIENTE[[#This Row],[FECHA]],"MMMM") -> julio | C37: =TEXT(CLIENTE[[#This Row],[FECHA]],"YYYY") -> 2018 | D37: 86 | E37: EL TESORO ENTRETENIMIENTO | F37: =VLOOKUP(CLIENTE[[#This Row],[CLIENTE]],Tabla5[],2,FALSE) -> 900.534.009-2 | G37: 190000 | H37: 0 | I37: =+G37-H37 -> 190000 | J37: REPARACION DE 2 BALONES Y TRASNPORTE | K37: 190000 | L37: =+CLIENTE[[#This Row],[VALOR]]-CLIENTE[[#This Row],[RTE FTE]]-CLIENTE[[#This Row],[Abono]] -> 0
A38: 43304 | B38: =TEXT(CLIENTE[[#This Row],[FECHA]],"MMMM") -> julio | C38: =TEXT(CLIENTE[[#This Row],[FECHA]],"YYYY") -> 2018 | D38: 87 | E38: EL TESORO ENTRETENIMIENTO | F38: =VLOOKUP(CLIENTE[[#This Row],[CLIENTE]],Tabla5[],2,FALSE) -> 900.534.009-2 | G38: 480000 | H38: 0 | I38: =+G38-H38 -> 480000 | J38: REPARACION DE 9 BALONES Y TRASNPORTE | K38: 480000 | L38: =+CLIENTE[[#This Row],[VALOR]]-CLIENTE[[#This Row],[RTE FTE]]-CLIENTE[[#This Row],[Abono]] -> 0
A39: 43307 | B39: =TEXT(CLIENTE[[#This Row],[FECHA]],"MMMM") -> julio | C39: =TEXT(CLIENTE[[#This Row],[FECHA]],"YYYY") -> 2018 | D39: 88 | E39: EL TESORO ENTRETENIMIENTO | F39: =VLOOKUP(CLIENTE[[#This Row],[CLIENTE]],Tabla5[],2,FALSE) -> 900.534.009-2 | G39: 380000 | H39: 0 | I39: =+G39-H39 -> 380000 | J39: REPARACION DE 7 BALONES Y TRANSPORTE | K39: 380000 | L39: =+CLIENTE[[#This Row],[VALOR]]-CLIENTE[[#This Row],[RTE FTE]]-CLIENTE[[#This Row],[Abono]] -> 0
A40: 43309 | B40: =TEXT(CLIENTE[[#This Row],[FECHA]],"MMMM") -> julio | C40: =TEXT(CLIENTE[[#This Row],[FECHA]],"YYYY") -> 2018 | D40: 89 | E40: EFITRANS | F40: =VLOOKUP(CLIENTE[[#This Row],[CLIENTE]],Tabla5[],2,FALSE) -> 811.028.194-4 | G40: 150000 | H40: 0 | I40: =+G40-H40 -> 150000 | J40: ARREGLO DE SOMBRILLAS | K40: 150000 | L40: =+CLIENTE[[#This Row],[VALOR]]-CLIENTE[[#This Row],[RTE FTE]]-CLIENTE[[#This Row],[Abono]] -> 0
A41: 43315 | B41: =TEXT(CLIENTE[[#This Row],[FECHA]],"MMMM") -> agosto | C41: =TEXT(CLIENTE[[#This Row],[FECHA]],"YYYY") -> 2018 | D41: 90 | E41: PLATAFORMA LOGISTICA Y COMERCIAL S.A.S | F41: =VLOOKUP(CLIENTE[[#This Row],[CLIENTE]],Tabla5[],2,FALSE) -> 901.092.692-9 | G41: 1200000 | H41: =+G41*3.5% -> 42000 | I41: =+G41-H41 -> 1158000 | J41: ALQUILER DE LOCAL CRA 49#86-04 , AGOSTO 2018 | K41: 1158000 | L41: =+CLIENTE[[#This Row],[VALOR]]-CLIENTE[[#This Row],[RTE FTE]]-CLIENTE[[#This Row],[Abono]] -> 0
A42: 43321 | B42: =TEXT(CLIENTE[[#This Row],[FECHA]],"MMMM") -> agosto | C42: =TEXT(CLIENTE[[#This Row],[FECHA]],"YYYY") -> 2018 | D42: 91 | E42: EL TESORO ENTRETENIMIENTO | F42: =VLOOKUP(CLIENTE[[#This Row],[CLIENTE]],Tabla5[],2,FALSE) -> 900.534.009-2 | G42: 630000 | H42: 0 | I42: =+G42-H42 -> 630000 | J42: REPARACION DE 12 BALONES Y TRASNPORTE | K42: 630000 | L42: =+CLIENTE[[#This Row],[VALOR]]-CLIENTE[[#This Row],[RTE FTE]]-CLIENTE[[#This Row],[Abono]] -> 0
A43: 43322 | B43: =TEXT(CLIENTE[[#This Row],[FECHA]],"MMMM") -> agosto | C43: =TEXT(CLIENTE[[#This Row],[FECHA]],"YYYY") -> 2018 | D43: 92 | E43: EL TESORO ENTRETENIMIENTO | F43: =VLOOKUP(CLIENTE[[#This Row],[CLIENTE]],Tabla5[],2,FALSE) -> 900.534.009-2 | G43: 280000 | H43: 0 | I43: =+G43-H43 -> 280000 | J43: REPARACION DE 5 BALONES Y TRASNPORTE | K43: 280000 | L43: =+CLIENTE[[#This Row],[VALOR]]-CLIENTE[[#This Row],[RTE FTE]]-CLIENTE[[#This Row],[Abono]] -> 0
A44: 43333 | B44: =TEXT(CLIENTE[[#This Row],[FECHA]],"MMMM") -> agosto | C44: =TEXT(CLIENTE[[#This Row],[FECHA]],"YYYY") -> 2018 | D44: 93 | E44: SINTRABANCOL | F44: =VLOOKUP(CLIENTE[[#This Row],[CLIENTE]],Tabla5[],2,FALSE) -> 860.013.526-9 | G44: 185000 | H44: 0 | I44: =+G44-H44 -> 185000 | J44: FORRO PROTECTOR ESTUFA INDUSTRIAL LONA HURACAN | K44: 185000 | L44: =+CLIENTE[[#This Row],[VALOR]]-CLIENTE[[#This Row],[RTE FTE]]-CLIENTE[[#This Row],[Abono]] -> 0
A45: 43335 | B45: =TEXT(CLIENTE[[#This Row],[FECHA]],"MMMM") -> agosto | C45: =TEXT(CLIENTE[[#This Row],[FECHA]],"YYYY") -> 2018 | D45: 94 | E45: FIJACIONES OROZCO S.A.S | F45: =VLOOKUP(CLIENTE[[#This Row],[CLIENTE]],Tabla5[],2,FALSE) -> 900.378.955-6 | G45: 100000 | H45: 0 | I45: =+G45-H45 -> 100000 | J45: COSTURA DE AVISO EN ENRROLLABLE | K45: 100000 | L45: =+CLIENTE[[#This Row],[VALOR]]-CLIENTE[[#This Row],[RTE FTE]]-CLIENTE[[#This Row],[Abono]] -> 0
A46: 43342 | B46: =TEXT(CLIENTE[[#This Row],[FECHA]],"MMMM") -> agosto | C46: =TEXT(CLIENTE[[#This Row],[FECHA]],"YYYY") -> 2018 | D46: 95 | E46: EL TESORO ENTRETENIMIENTO | F46: =VLOOKUP(CLIENTE[[#This Row],[CLIENTE]],Tabla5[],2,FALSE) -> 900.534.009-2 | G46: 380000 | H46: 0 | I46: =+G46-H46 -> 380000 | J46: REPARACION DE 7 BALONES Y TRANSPORTE | K46: 380000 | L46: =+CLIENTE[[#This Row],[VALOR]]-CLIENTE[[#This Row],[RTE FTE]]-CLIENTE[[#This Row],[Abono]] -> 0
A47: 43346 | B47: =TEXT(CLIENTE[[#This Row],[FECHA]],"MMMM") -> septiembre | C47: =TEXT(CLIENTE[[#This Row],[FECHA]],"YYYY") -> 2018 | D47: 96 | E47: PLATAFORMA LOGISTICA Y COMERCIAL S.A.S | F47: =VLOOKUP(CLIENTE[[#This Row],[CLIENTE]],Tabla5[],2,FALSE) -> 901.092.692-9 | G47: 1200000 | H47: =+G47*3.5% -> 42000 | I47: =+G47-H47 -> 1158000 | J47: ALQUILER DE LOCAL CRA 49#86-04 , SEPTIEMBRE 2018 | K47: 1158000 | L47: =+CLIENTE[[#This Row],[VALOR]]-CLIENTE[[#This Row],[RTE FTE]]-CLIENTE[[#This Row],[Abono]] -> 0
A48: 43355 | B48: =TEXT(CLIENTE[[#This Row],[FECHA]],"MMMM") -> septiembre | C48: =TEXT(CLIENTE[[#This Row],[FECHA]],"YYYY") -> 2018 | D48: 97 | E48: EL TESORO ENTRETENIMIENTO | F48: =VLOOKUP(CLIENTE[[#This Row],[CLIENTE]],Tabla5[],2,FALSE) -> 900.534.009-2 | G48: 480000 | H48: 0 | I48: =+G48-H48 -> 480000 | J48: REPARACION DE 9 BALONES Y TRASNPORTE | K48: 480000 | L48: =+CLIENTE[[#This Row],[VALOR]]-CLIENTE[[#This Row],[RTE FTE]]-CLIENTE[[#This Row],[Abono]] -> 0
A49: 43361 | B49: =TEXT(CLIENTE[[#This Row],[FECHA]],"MMMM") -> septiembre | C49: =TEXT(CLIENTE[[#This Row],[FECHA]],"YYYY") -> 2018 | D49: 98 | E49: GABRIEL ARTURO ALZATE | F49: =VLOOKUP(CLIENTE[[#This Row],[CLIENTE]],Tabla5[],2,FALSE) -> 8.277.443-8 | G49: 2000000 | H49: =+G49*6% -> 120000 | I49: =+G49-H49 -> 1880000 | J49: PROTECCION DE MURO OBRA EL BOSQUEEN LONA ACRILICA | K49: 1880000 | L49: =+CLIENTE[[#This Row],[VALOR]]-CLIENTE[[#This Row],[RTE FTE]]-CLIENTE[[#This Row],[Abono]] -> 0
A50: 43370 | B50: =TEXT(CLIENTE[[#This Row],[FECHA]],"MMMM") -> septiembre | C50: =TEXT(CLIENTE[[#This Row],[FECHA]],"YYYY") -> 2018 | D50: 99 | E50: CARLOS MARIO MOLINA V | F50: =VLOOKUP(CLIENTE[[#This Row],[CLIENTE]],Tabla5[],2,FALSE) -> 98.640.058-9 | G50: 400000 | H50: 0 | I50: =+G50-H50 -> 400000 | J50: PROTECTOR JACUZZI ED. FUENTE CLARA | K50: 400000 | L50: =+CLIENTE[[#This Row],[VALOR]]-CLIENTE[[#This Row],[RTE FTE]]-CLIENTE[[#This Row],[Abono]] -> 0
A51: 43375 | B51: =TEXT(CLIENTE[[#This Row],[FECHA]],"MMMM") -> octubre | C51: =TEXT(CLIENTE[[#This Row],[FECHA]],"YYYY") -> 2018 | D51: 100 | E51: PLATAFORMA LOGISTICA Y COMERCIAL S.A.S | F51: =VLOOKUP(CLIENTE[[#This Row],[CLIENTE]],Tabla5[],2,FALSE) -> 901.092.692-9 | G51: 1200000 | H51: =+G51*3.5% -> 42000 | I51: =+G51-H51 -> 1158000 | J51: ALQUILER DE LOCAL CRA 49#86-04 , OCTUBRE 2018 | K51: 1158000 | L51: =+CLIENTE[[#This Row],[VALOR]]-CLIENTE[[#This Row],[RTE FTE]]-CLIENTE[[#This Row],[Abono]] -> 0
A52: 43375 | B52: =TEXT(CLIENTE[[#This Row],[FECHA]],"MMMM") -> octubre | C52: =TEXT(CLIENTE[[#This Row],[FECHA]],"YYYY") -> 2018 | D52: 101 | E52: EL TESORO ENTRETENIMIENTO | F52: =VLOOKUP(CLIENTE[[#This Row],[CLIENTE]],Tabla5[],2,FALSE) -> 900.534.009-2 | G52: 380000 | H52: 0 | I52: =+G52-H52 -> 380000 | J52: REPARACION DE 7 BALONES Y TRANSPORTE | K52: 380000 | L52: =+CLIENTE[[#This Row],[VALOR]]-CLIENTE[[#This Row],[RTE FTE]]-CLIENTE[[#This Row],[Abono]] -> 0
A53: 43383 | B53: =TEXT(CLIENTE[[#This Row],[FECHA]],"MMMM") -> octubre | C53: =TEXT(CLIENTE[[#This Row],[FECHA]],"YYYY") -> 2018 | D53: 102 | E53: EL TESORO ENTRETENIMIENTO | F53: =VLOOKUP(CLIENTE[[#This Row],[CLIENTE]],Tabla5[],2,FALSE) -> 900.534.009-2 | G53: 330000 | H53: 0 | I53: =+G53-H53 -> 330000 | J53: REPARACION DE 6 BALONES Y TRANSPORTE | K53: 330000 | L53: =+CLIENTE[[#This Row],[VALOR]]-CLIENTE[[#This Row],[RTE FTE]]-CLIENTE[[#This Row],[Abono]] -> 0
A54: 43385 | B54: =TEXT(CLIENTE[[#This Row],[FECHA]],"MMMM") -> octubre | C54: =TEXT(CLIENTE[[#This Row],[FECHA]],"YYYY") -> 2018 | D54: 103 | E54: EL TESORO ENTRETENIMIENTO | F54: =VLOOKUP(CLIENTE[[#This Row],[CLIENTE]],Tabla5[],2,FALSE) -> 900.534.009-2 | G54: 330000 | H54: 0 | I54: =+G54-H54 -> 330000 | J54: REPARACION DE 6 BALONES Y TRANSPORTE | K54: 330000 | L54: =+CLIENTE[[#This Row],[VALOR]]-CLIENTE[[#This Row],[RTE FTE]]-CLIENTE[[#This Row],[Abono]] -> 0
A55: 43405 | B55: =TEXT(CLIENTE[[#This Row],[FECHA]],"MMMM") -> noviembre | C55: =TEXT(CLIENTE[[#This Row],[FECHA]],"YYYY") -> 2018 | D55: 104 | E55: EL TESORO ENTRETENIMIENTO | F55: =VLOOKUP(CLIENTE[[#This Row],[CLIENTE]],Tabla5[],2,FALSE) -> 900.534.009-2 | G55: 280000 | H55: 0 | I55: =+G55-H55 -> 280000 | J55: REPARACION DE 5 BALONES Y TRASNPORTE | K55: 280000 | L55: =+CLIENTE[[#This Row],[VALOR]]-CLIENTE[[#This Row],[RTE FTE]]-CLIENTE[[#This Row],[Abono]] -> 0
A56: 43406 | B56: =TEXT(CLIENTE[[#This Row],[FECHA]],"MMMM") -> noviembre | C56: =TEXT(CLIENTE[[#This Row],[FECHA]],"YYYY") -> 2018 | D56: 105 | E56: PLATAFORMA LOGISTICA Y COMERCIAL S.A.S | F56: =VLOOKUP(CLIENTE[[#This Row],[CLIENTE]],Tabla5[],2,FALSE) -> 901.092.692-9 | G56: 1200000 | H56: 42000 | I56: =+G56-H56 -> 1158000 | J56: ALQUILER DE LOCAL CRA 49#86-04 , NOVIEMBRE 2018 | K56: 1158000 | L56: =+CLIENTE[[#This Row],[VALOR]]-CLIENTE[[#This Row],[RTE FTE]]-CLIENTE[[#This Row],[Abono]] -> 0
A57: 43409 | B57: =TEXT(CLIENTE[[#This Row],[FECHA]],"MMMM") -> noviembre | C57: =TEXT(CLIENTE[[#This Row],[FECHA]],"YYYY") -> 2018 | D57: 106 | E57: EL TESORO ENTRETENIMIENTO | F57: =VLOOKUP(CLIENTE[[#This Row],[CLIENTE]],Tabla5[],2,FALSE) -> 900.534.009-2 | G57: 380000 | H57: 0 | I57: =+G57-H57 -> 380000 | J57: REPARACION DE 7 BALONES Y TRANSPORTE | K57: 380000 | L57: =+CLIENTE[[#This Row],[VALOR]]-CLIENTE[[#This Row],[RTE FTE]]-CLIENTE[[#This Row],[Abono]] -> 0
A58: 43412 | B58: =TEXT(CLIENTE[[#This Row],[FECHA]],"MMMM") -> noviembre | C58: =TEXT(CLIENTE[[#This Row],[FECHA]],"YYYY") -> 2018 | D58: 107 | E58: EL TESORO ENTRETENIMIENTO | F58: =VLOOKUP(CLIENTE[[#This Row],[CLIENTE]],Tabla5[],2,FALSE) -> 900.534.009-2 | G58: 280000 | H58: 0 | I58: =+G58-H58 -> 280000 | J58: REPARACION DE 5 BALONES Y TRASNPORTE | K58: 280000 | L58: =+CLIENTE[[#This Row],[VALOR]]-CLIENTE[[#This Row],[RTE FTE]]-CLIENTE[[#This Row],[Abono]] -> 0
A59: 43426 | B59: =TEXT(CLIENTE[[#This Row],[FECHA]],"MMMM") -> noviembre | C59: =TEXT(CLIENTE[[#This Row],[FECHA]],"YYYY") -> 2018 | D59: 108 | E59: EL TESORO ENTRETENIMIENTO | F59: =VLOOKUP(CLIENTE[[#This Row],[CLIENTE]],Tabla5[],2,FALSE) -> 900.534.009-2 | G59: 380000 | H59: 0 | I59: =+G59-H59 -> 380000 | J59: REPARACION DE 7 BALONES Y TRANSPORTE | K59: 380000 | L59: =+CLIENTE[[#This Row],[VALOR]]-CLIENTE[[#This Row],[RTE FTE]]-CLIENTE[[#This Row],[Abono]] -> 0
A60: 43435 | B60: =TEXT(CLIENTE[[#This Row],[FECHA]],"MMMM") -> diciembre | C60: =TEXT(CLIENTE[[#This Row],[FECHA]],"YYYY") -> 2018 | D60: 109 | E60: PLATAFORMA LOGISTICA Y COMERCIAL S.A.S | F60: =VLOOKUP(CLIENTE[[#This Row],[CLIENTE]],Tabla5[],2,FALSE) -> 901.092.692-9 | G60: 1200000 | H60: 42000 | I60: =+G60-H60 -> 1158000 | J60: ALQUILER DE LOCAL CRA 49#86-04 , DICIEMBRE 2018 | K60: 1158000 | L60: =+CLIENTE[[#This Row],[VALOR]]-CLIENTE[[#This Row],[RTE FTE]]-CLIENTE[[#This Row],[Abono]] -> 0
A61: 43437 | B61: =TEXT(CLIENTE[[#This Row],[FECHA]],"MMMM") -> diciembre | C61: =TEXT(CLIENTE[[#This Row],[FECHA]],"YYYY") -> 2018 | D61: 110 | E61: EL TESORO ENTRETENIMIENTO | F61: =VLOOKUP(CLIENTE[[#This Row],[CLIENTE]],Tabla5[],2,FALSE) -> 900.534.009-2 | G61: 400000 | H61: 0 | I61: =+G61-H61 -> 400000 | J61: REPARACION DE 6 BALONES, 1 BALON CORREAS Y TRANSPORTE | K61: 400000 | L61: =+CLIENTE[[#This Row],[VALOR]]-CLIENTE[[#This Row],[RTE FTE]]-CLIENTE[[#This Row],[Abono]] -> 0
A62: 43442 | B62: =TEXT(CLIENTE[[#This Row],[FECHA]],"MMMM") -> diciembre | C62: =TEXT(CLIENTE[[#This Row],[FECHA]],"YYYY") -> 2018 | D62: 111 | E62: EL TESORO ENTRETENIMIENTO | F62: =VLOOKUP(CLIENTE[[#This Row],[CLIENTE]],Tabla5[],2,FALSE) -> 900.534.009-2 | G62: 333000 | H62: 0 | I62: =+G62-H62 -> 333000 | J62: REPARACION DE 6 BALONES Y TRANSPORTE | K62: 333000 | L62: =+CLIENTE[[#This Row],[VALOR]]-CLIENTE[[#This Row],[RTE FTE]]-CLIENTE[[#This Row],[Abono]] -> 0
A63: 43454 | B63: =TEXT(CLIENTE[[#This Row],[FECHA]],"MMMM") -> diciembre | C63: =TEXT(CLIENTE[[#This Row],[FECHA]],"YYYY") -> 2018 | D63: 112 | E63: EL TESORO ENTRETENIMIENTO | F63: =VLOOKUP(CLIENTE[[#This Row],[CLIENTE]],Tabla5[],2,FALSE) -> 900.534.009-2 | G63: 280000 | H63: 0 | I63: =+G63-H63 -> 280000 | J63: REPARACION DE 5 BALONES Y TRASNPORTE | K63: 280000 | L63: =+CLIENTE[[#This Row],[VALOR]]-CLIENTE[[#This Row],[RTE FTE]]-CLIENTE[[#This Row],[Abono]] -> 0
... A65: 43825 | B65: =TEXT(CLIENTE[[#This Row],[FECHA]],"MMMM") -> diciembre | C65: =TEXT(CLIENTE[[#This Row],[FECHA]],"YYYY") -> 2019 | D65: 114 | E65: EL TESORO ENTRETENIMIENTO | F65: =VLOOKUP(CLIENTE[[#This Row],[CLIENTE]],Tabla5[],2,FALSE) -> 900.534.009-2 | G65: 230000 | H65: 0 | I65: =+G65-H65 -> 230000 | J65: REPARACION DE 4 BALONES Y TARSNPORTE | K65: 230000 | L65: =+CLIENTE[[#This Row],[VALOR]]-CLIENTE[[#This Row],[RTE FTE]]-CLIENTE[[#This Row],[Abono]] -> 0
A66: 43467 | B66: =TEXT(CLIENTE[[#This Row],[FECHA]],"MMMM") -> enero | C66: =TEXT(CLIENTE[[#This Row],[FECHA]],"YYYY") -> 2019 | D66: 115 | E66: PLATAFORMA LOGISTICA Y COMERCIAL S.A.S | F66: =VLOOKUP(CLIENTE[[#This Row],[CLIENTE]],Tabla5[],2,FALSE) -> 901.092.692-9 | G66: 1200000 | H66: =+G66*3.5% -> 42000 | I66: =+G66-H66 -> 1158000 | J66: ALQUILER DE LOCAL CRA 49#86-04 , ENERO 2019 | K66: 1158000 | L66: =+CLIENTE[[#This Row],[VALOR]]-CLIENTE[[#This Row],[RTE FTE]]-CLIENTE[[#This Row],[Abono]] -> 0
A67: 43468 | B67: =TEXT(CLIENTE[[#This Row],[FECHA]],"MMMM") -> enero | C67: =TEXT(CLIENTE[[#This Row],[FECHA]],"YYYY") -> 2019 | D67: 116 | E67: EL TESORO ENTRETENIMIENTO | F67: =VLOOKUP(CLIENTE[[#This Row],[CLIENTE]],Tabla5[],2,FALSE) -> 900.534.009-2 | G67: 330000 | H67: 0 | I67: =+G67-H67 -> 330000 | J67: REPARACION DE 6 BALONES Y TRANSPORTE | K67: 330000 | L67: =+CLIENTE[[#This Row],[VALOR]]-CLIENTE[[#This Row],[RTE FTE]]-CLIENTE[[#This Row],[Abono]] -> 0
A68: 43480 | B68: =TEXT(CLIENTE[[#This Row],[FECHA]],"MMMM") -> enero | C68: =TEXT(CLIENTE[[#This Row],[FECHA]],"YYYY") -> 2019 | D68: 117 | E68: EL TESORO ENTRETENIMIENTO | F68: =VLOOKUP(CLIENTE[[#This Row],[CLIENTE]],Tabla5[],2,FALSE) -> 900.534.009-2 | G68: 330000 | H68: 0 | I68: =+G68-H68 -> 330000 | J68: REPARACION DE 6 BALONES Y TRANSPORTE | K68: 330000 | L68: =+CLIENTE[[#This Row],[VALOR]]-CLIENTE[[#This Row],[RTE FTE]]-CLIENTE[[#This Row],[Abono]] -> 0
A69: 43498 | B69: =TEXT(CLIENTE[[#This Row],[FECHA]],"MMMM") -> febrero | C69: =TEXT(CLIENTE[[#This Row],[FECHA]],"YYYY") -> 2019 | D69: 118 | E69: PLATAFORMA LOGISTICA Y COMERCIAL S.A.S | F69: =VLOOKUP(CLIENTE[[#This Row],[CLIENTE]],Tabla5[],2,FALSE) -> 901.092.692-9 | G69: 1200000 | H69: =+G69*3.5% -> 42000 | I69: =+G69-H69 -> 1158000 | J69: ALQUILER DE LOCAL CRA 49#86-04 , FEBRERO 2019 | K69: 1158000 | L69: =+CLIENTE[[#This Row],[VALOR]]-CLIENTE[[#This Row],[RTE FTE]]-CLIENTE[[#This Row],[Abono]] -> 0
A70: 43500 | B70: =TEXT(CLIENTE[[#This Row],[FECHA]],"MMMM") -> febrero | C70: =TEXT(CLIENTE[[#This Row],[FECHA]],"YYYY") -> 2019 | D70: 119 | E70: EL TESORO ENTRETENIMIENTO | F70: =VLOOKUP(CLIENTE[[#This Row],[CLIENTE]],Tabla5[],2,FALSE) -> 900.534.009-2 | G70: 240000 | H70: 0 | I70: =+G70-H70 -> 240000 | J70: REPARACION DE 4 BALONES Y TRANSPORTE | K70: 240000 | L70: =+CLIENTE[[#This Row],[VALOR]]-CLIENTE[[#This Row],[RTE FTE]]-CLIENTE[[#This Row],[Abono]] -> 0
A71: 43525 | B71: =TEXT(CLIENTE[[#This Row],[FECHA]],"MMMM") -> marzo | C71: =TEXT(CLIENTE[[#This Row],[FECHA]],"YYYY") -> 2019 | D71: 120 | E71: PLATAFORMA LOGISTICA Y COMERCIAL S.A.S | F71: =VLOOKUP(CLIENTE[[#This Row],[CLIENTE]],Tabla5[],2,FALSE) -> 901.092.692-9 | G71: 1200000 | H71: =+G71*3.5% -> 42000 | I71: =+G71-H71 -> 1158000 | J71: ALQUILER DE LOCAL CRA 49#86-04 , MARZO 2019 | K71: 1158000 | L71: =+CLIENTE[[#This Row],[VALOR]]-CLIENTE[[#This Row],[RTE FTE]]-CLIENTE[[#This Row],[Abono]] -> 0
A72: 43540 | B72: =TEXT(CLIENTE[[#This Row],[FECHA]],"MMMM") -> marzo | C72: =TEXT(CLIENTE[[#This Row],[FECHA]],"YYYY") -> 2019 | D72: 121 | E72: EL TESORO ENTRETENIMIENTO | F72: =VLOOKUP(CLIENTE[[#This Row],[CLIENTE]],Tabla5[],2,FALSE) -> 900.534.009-2 | G72: 80000 | H72: 0 | I72: =+G72-H72 -> 80000 | J72: REPARACION DE PUERTA BRINCA BRINCA | K72: 80000 | L72: =+CLIENTE[[#This Row],[VALOR]]-CLIENTE[[#This Row],[RTE FTE]]-CLIENTE[[#This Row],[Abono]] -> 0
A73: 43556 | B73: =TEXT(CLIENTE[[#This Row],[FECHA]],"MMMM") -> abril | C73: =TEXT(CLIENTE[[#This Row],[FECHA]],"YYYY") -> 2019 | D73: 122 | E73: PLATAFORMA LOGISTICA Y COMERCIAL S.A.S | F73: =VLOOKUP(CLIENTE[[#This Row],[CLIENTE]],Tabla5[],2,FALSE) -> 901.092.692-9 | G73: 1200000 | H73: =+G73*3.5% -> 42000 | I73: =+G73-H73 -> 1158000 | J73: ALQUILER DE LOCAL CRA 49#86-04 , ABRIL 2019 | K73: 1158000 | L73: =+CLIENTE[[#This Row],[VALOR]]-CLIENTE[[#This Row],[RTE FTE]]-CLIENTE[[#This Row],[Abono]] -> 0
A74: 43563 | B74: =TEXT(CLIENTE[[#This Row],[FECHA]],"MMMM") -> abril | C74: =TEXT(CLIENTE[[#This Row],[FECHA]],"YYYY") -> 2019 | D74: 123 | E74: REIMPEX S.A | F74: =VLOOKUP(CLIENTE[[#This Row],[CLIENTE]],Tabla5[],2,FALSE) -> 890.939.592-0 | G74: 240000 | H74: =+G74*3.5% -> 8400 | I74: =+G74-H74 -> 231600 | J74: 3 HORAS DE INDUCCION DE SELLADORA | K74: 231600 | L74: =+CLIENTE[[#This Row],[VALOR]]-CLIENTE[[#This Row],[RTE FTE]]-CLIENTE[[#This Row],[Abono]] -> 0
A75: 43581 | B75: =TEXT(CLIENTE[[#This Row],[FECHA]],"MMMM") -> abril | C75: =TEXT(CLIENTE[[#This Row],[FECHA]],"YYYY") -> 2019 | D75: 124 | E75: REIMPEX S.A | F75: =VLOOKUP(CLIENTE[[#This Row],[CLIENTE]],Tabla5[],2,FALSE) -> 890.939.592-0 | G75: 165000 | H75: =+G75*3.5% -> 5775 | I75: =+G75-H75 -> 159225 | J75: MANO DE OBRA ELABORACION DE 3 CORTINAS | K75: 159225 | L75: =+CLIENTE[[#This Row],[VALOR]]-CLIENTE[[#This Row],[RTE FTE]]-CLIENTE[[#This Row],[Abono]] -> 0
A76: 43587 | B76: =TEXT(CLIENTE[[#This Row],[FECHA]],"MMMM") -> mayo | C76: =TEXT(CLIENTE[[#This Row],[FECHA]],"YYYY") -> 2019 | D76: 125 | E76: PLATAFORMA LOGISTICA Y COMERCIAL S.A.S | F76: =VLOOKUP(CLIENTE[[#This Row],[CLIENTE]],Tabla5[],2,FALSE) -> 901.092.692-9 | G76: 1284000 | H76: =+G76*3.5% -> 44940 | I76: =+G76-H76 -> 1239060 | J76: ALQUILER DE LOCAL CRA 49#86-04 , MAYO 2019 | K76: 1239060 | L76: =+CLIENTE[[#This Row],[VALOR]]-CLIENTE[[#This Row],[RTE FTE]]-CLIENTE[[#This Row],[Abono]] -> 0
A77: 43617 | B77: =TEXT(CLIENTE[[#This Row],[FECHA]],"MMMM") -> junio | C77: =TEXT(CLIENTE[[#This Row],[FECHA]],"YYYY") -> 2019 | D77: 126 | E77: PLATAFORMA LOGISTICA Y COMERCIAL S.A.S | F77: =VLOOKUP(CLIENTE[[#This Row],[CLIENTE]],Tabla5[],2,FALSE) -> 901.092.692-9 | G77: 1284000 | H77: =+G77*3.5% -> 44940 | I77: =+G77-H77 -> 1239060 | J77: ALQUILER DE LOCAL CRA 49#86-04 , JUNIO 2019 | K77: 1239060 | L77: =+CLIENTE[[#This Row],[VALOR]]-CLIENTE[[#This Row],[RTE FTE]]-CLIENTE[[#This Row],[Abono]] -> 0
A78: 43648 | B78: =TEXT(CLIENTE[[#This Row],[FECHA]],"MMMM") -> julio | C78: =TEXT(CLIENTE[[#This Row],[FECHA]],"YYYY") -> 2019 | D78: 127 | E78: PLATAFORMA LOGISTICA Y COMERCIAL S.A.S | F78: =VLOOKUP(CLIENTE[[#This Row],[CLIENTE]],Tabla5[],2,FALSE) -> 901.092.692-9 | G78: 1284000 | H78: =+G78*3.5% -> 44940 | I78: =+G78-H78 -> 1239060 | J78: ALQUILER DE LOCAL CRA 49#86-04 , JULIO 2019 | K78: 1239060 | L78: =+CLIENTE[[#This Row],[VALOR]]-CLIENTE[[#This Row],[RTE FTE]]-CLIENTE[[#This Row],[Abono]] -> 0
A79: 43671 | B79: =TEXT(CLIENTE[[#This Row],[FECHA]],"MMMM") -> julio | C79: =TEXT(CLIENTE[[#This Row],[FECHA]],"YYYY") -> 2019 | D79: 128 | E79: CENTRO MEDICO VETERINARIO BELLOS CANES | F79: =VLOOKUP(CLIENTE[[#This Row],[CLIENTE]],Tabla5[],2,FALSE) -> 901.061.785-2 | G79: 30000 | H79: 0 | I79: =+G79-H79 -> 30000 | J79: FABRICACION DE DESCANSA PIES | K79: 30000 | L79: =+CLIENTE[[#This Row],[VALOR]]-CLIENTE[[#This Row],[RTE FTE]]-CLIENTE[[#This Row],[Abono]] -> 0
A80: 43678 | B80: =TEXT(CLIENTE[[#This Row],[FECHA]],"MMMM") -> agosto | C80: =TEXT(CLIENTE[[#This Row],[FECHA]],"YYYY") -> 2019 | D80: 130 | E80: PLATAFORMA LOGISTICA Y COMERCIAL S.A.S | F80: =VLOOKUP(CLIENTE[[#This Row],[CLIENTE]],Tabla5[],2,FALSE) -> 901.092.692-9 | G80: 1284000 | H80: =+G80*3.5% -> 44940 | I80: =+G80-H80 -> 1239060 | J80: ALQUILER DE LOCAL CRA 49#86-04 , AGOSTO 2019 | K80: 1239060 | L80: =+CLIENTE[[#This Row],[VALOR]]-CLIENTE[[#This Row],[RTE FTE]]-CLIENTE[[#This Row],[Abono]] -> 0
A81: 43685 | B81: =TEXT(CLIENTE[[#This Row],[FECHA]],"MMMM") -> agosto | C81: =TEXT(CLIENTE[[#This Row],[FECHA]],"YYYY") -> 2019 | D81: 131 | E81: EFITRANS S.A.S | F81: =VLOOKUP(CLIENTE[[#This Row],[CLIENTE]],Tabla5[],2,FALSE) -> 811.028.194-4 | G81: 820000 | H81: 0 | I81: =+G81-H81 -> 820000 | J81: CARPA 4X4 EN BRIGADIER CON PUBLICIDAD, PINTURA DE ESTRUCTURA | K81: 820000 | L81: =+CLIENTE[[#This Row],[VALOR]]-CLIENTE[[#This Row],[RTE FTE]]-CLIENTE[[#This Row],[Abono]] -> 0
A82: 43709 | B82: =TEXT(CLIENTE[[#This Row],[FECHA]],"MMMM") -> septiembre | C82: =TEXT(CLIENTE[[#This Row],[FECHA]],"YYYY") -> 2019 | D82: 132 | E82: PLATAFORMA LOGISTICA Y COMERCIAL S.A.S | F82: =VLOOKUP(CLIENTE[[#This Row],[CLIENTE]],Tabla5[],2,FALSE) -> 901.092.692-9 | G82: 1284000 | H82: =+G82*3.5% -> 44940 | I82: =+G82-H82 -> 1239060 | J82: ALQUILER DE LOCAL CRA 49#86-04 , SEPTIEMBRE 2019 | K82: 1239060 | L82: =+CLIENTE[[#This Row],[VALOR]]-CLIENTE[[#This Row],[RTE FTE]]-CLIENTE[[#This Row],[Abono]] -> 0
A83: 43739 | B83: =TEXT(CLIENTE[[#This Row],[FECHA]],"MMMM") -> octubre | C83: =TEXT(CLIENTE[[#This Row],[FECHA]],"YYYY") -> 2019 | D83: 133 | E83: PLATAFORMA LOGISTICA Y COMERCIAL S.A.S | F83: =VLOOKUP(CLIENTE[[#This Row],[CLIENTE]],Tabla5[],2,FALSE) -> 901.092.692-9 | G83: 1284000 | H83: =+G83*3.5% -> 44940 | I83: =+G83-H83 -> 1239060 | J83: ALQUILER DE LOCAL CRA 49#86-04 , OCTUBRE 2019 | K83: 1239060 | L83: =+CLIENTE[[#This Row],[VALOR]]-CLIENTE[[#This Row],[RTE FTE]]-CLIENTE[[#This Row],[Abono]] -> 0
A84: 43826 | B84: =TEXT(CLIENTE[[#This Row],[FECHA]],"MMMM") -> diciembre | C84: =TEXT(CLIENTE[[#This Row],[FECHA]],"YYYY") -> 2019 | D84: 134 | E84: INGENIERIA EFICIENTE DEL AIRE S.A.S | F84: =VLOOKUP(CLIENTE[[#This Row],[CLIENTE]],Tabla5[],2,FALSE) -> 900.729.224-8 | G84: 270000 | H84: 0 | I84: =+G84-H84 -> 270000 | J84: 4 JUNTAS CIRCULARES $52.000--1 JUNTA RECTAGULAR $ 62.000 | K84: 270000 | L84: =+CLIENTE[[#This Row],[VALOR]]-CLIENTE[[#This Row],[RTE FTE]]-CLIENTE[[#This Row],[Abono]] -> 0
A85: 43955 | B85: =TEXT(CLIENTE[[#This Row],[FECHA]],"MMMM") -> mayo | C85: =TEXT(CLIENTE[[#This Row],[FECHA]],"YYYY") -> 2020 | D85: 135 | E85: TRANSPORTE Y TURISMO 1A S.A.S | F85: =VLOOKUP(CLIENTE[[#This Row],[CLIENTE]],Tabla5[],2,FALSE) -> 811.010.604-3 | G85: 396000 | H85: 15840 | I85: =+G85-H85 -> 380160 | J85: CORTINAS PROTECTORAS VEHICULOS 8 LOGAN-4 DUSTER $33.000 | K85: 380160 | L85: =+CLIENTE[[#This Row],[VALOR]]-CLIENTE[[#This Row],[RTE FTE]]-CLIENTE[[#This Row],[Abono]] -> 0
A86: 43983 | B86: =TEXT(CLIENTE[[#This Row],[FECHA]],"MMMM") -> junio | C86: =TEXT(CLIENTE[[#This Row],[FECHA]],"YYYY") -> 2020 | D86: 136 | E86: ELEVEMOS S.A.S | F86: =VLOOKUP(CLIENTE[[#This Row],[CLIENTE]],Tabla5[],2,FALSE) -> 900.790.148-4 | G86: 260000 | H86: 0 | I86: =+G86-H86 -> 260000 | J86: 20 PROTECTORES BOTONERAS INTERNA$13.000 | K86: 260000 | L86: =+CLIENTE[[#This Row],[VALOR]]-CLIENTE[[#This Row],[RTE FTE]]-CLIENTE[[#This Row],[Abono]] -> 0
A87: 43987 | B87: =TEXT(CLIENTE[[#This Row],[FECHA]],"MMMM") -> junio | C87: =TEXT(CLIENTE[[#This Row],[FECHA]],"YYYY") -> 2020 | D87: 137 | E87: ELEVEMOS S.A.S | F87: =VLOOKUP(CLIENTE[[#This Row],[CLIENTE]],Tabla5[],2,FALSE) -> 900.790.148-4 | G87: 550000 | H87: 0 | I87: =+G87-H87 -> 550000 | J87: 100 PROTECTORES BOTONERAS EXTERNAS $5.000 | K87: 550000 | L87: =+CLIENTE[[#This Row],[VALOR]]-CLIENTE[[#This Row],[RTE FTE]]-CLIENTE[[#This Row],[Abono]] -> 0
A88: 44009 | B88: =TEXT(CLIENTE[[#This Row],[FECHA]],"MMMM") -> junio | C88: =TEXT(CLIENTE[[#This Row],[FECHA]],"YYYY") -> 2020 | D88: 138 | E88: ELEVEMOS S.A.S | F88: =VLOOKUP(CLIENTE[[#This Row],[CLIENTE]],Tabla5[],2,FALSE) -> 900.790.148-4 | G88: 1440000 | H88: 0 | I88: =+G88-H88 -> 1440000 | J88: 3 LONAS PROTECTORAS UND. PUERTO MADERA | K88: 1440000 | L88: =+CLIENTE[[#This Row],[VALOR]]-CLIENTE[[#This Row],[RTE FTE]]-CLIENTE[[#This Row],[Abono]] -> 0
A89: 44015 | B89: =TEXT(CLIENTE[[#This Row],[FECHA]],"MMMM") -> julio | C89: =TEXT(CLIENTE[[#This Row],[FECHA]],"YYYY") -> 2020 | D89: 139 | E89: ELEVEMOS S.A.S | F89: =VLOOKUP(CLIENTE[[#This Row],[CLIENTE]],Tabla5[],2,FALSE) -> 900.790.148-4 | G89: 300000 | H89: 0 | I89: =+G89-H89 -> 300000 | J89: 60 PROTECTORES EXTERNOS $5.000 | K89: 300000 | L89: =+CLIENTE[[#This Row],[VALOR]]-CLIENTE[[#This Row],[RTE FTE]]-CLIENTE[[#This Row],[Abono]] -> 0
A90: 44020 | B90: =TEXT(CLIENTE[[#This Row],[FECHA]],"MMMM") -> julio | C90: =TEXT(CLIENTE[[#This Row],[FECHA]],"YYYY") -> 2020 | D90: 140 | E90: ELEVEMOS S.A.S | F90: =VLOOKUP(CLIENTE[[#This Row],[CLIENTE]],Tabla5[],2,FALSE) -> 900.790.148-4 | G90: 80000 | H90: 0 | I90: =+G90-H90 -> 80000 | J90: PROTECTOR PARA MESA | K90: 80000 | L90: =+CLIENTE[[#This Row],[VALOR]]-CLIENTE[[#This Row],[RTE FTE]]-CLIENTE[[#This Row],[Abono]] -> 0
A91: 44047 | B91: =TEXT(CLIENTE[[#This Row],[FECHA]],"MMMM") -> agosto | C91: =TEXT(CLIENTE[[#This Row],[FECHA]],"YYYY") -> 2020 | D91: 141 | E91: HECKCACOL SERVICIOS INDUSTRIALES S.A.S | F91: =VLOOKUP(CLIENTE[[#This Row],[CLIENTE]],Tabla5[],2,FALSE) -> 900.678.158-1 | G91: 630000 | H91: 0 | I91: =+G91-H91 -> 630000 | J91: LONA PROTECTORA CAÑAVERAL | K91: 630000 | L91: =+CLIENTE[[#This Row],[VALOR]]-CLIENTE[[#This Row],[RTE FTE]]-CLIENTE[[#This Row],[Abono]] -> 0
A92: 44055 | B92: =TEXT(CLIENTE[[#This Row],[FECHA]],"MMMM") -> agosto | C92: =TEXT(CLIENTE[[#This Row],[FECHA]],"YYYY") -> 2020 | D92: 142 | E92: ELEVEMOS S.A.S | F92: =VLOOKUP(CLIENTE[[#This Row],[CLIENTE]],Tabla5[],2,FALSE) -> 900.790.148-4 | G92: 260000 | H92: 0 | I92: =+G92-H92 -> 260000 | J92: 20 PROTECTORES BOTONERAS INTERNA$13.000 | K92: 260000 | L92: =+CLIENTE[[#This Row],[VALOR]]-CLIENTE[[#This Row],[RTE FTE]]-CLIENTE[[#This Row],[Abono]] -> 0
A93: 44067 | B93: =TEXT(CLIENTE[[#This Row],[FECHA]],"MMMM") -> agosto | C93: =TEXT(CLIENTE[[#This Row],[FECHA]],"YYYY") -> 2020 | D93: 143 | E93: PROELECTRA DE COLOMBIA S.A.S | F93: =VLOOKUP(CLIENTE[[#This Row],[CLIENTE]],Tabla5[],2,FALSE) -> 900.531.259-3 | G93: 386000 | H93: 0 | I93: =+G93-H93 -> 386000 | J93: 3 JD PROTECTOR SOLDADOR | K93: 386000 | L93: =+CLIENTE[[#This Row],[VALOR]]-CLIENTE[[#This Row],[RTE FTE]]-CLIENTE[[#This Row],[Abono]] -> 0
A94: 44088 | B94: =TEXT(CLIENTE[[#This Row],[FECHA]],"MMMM") -> septiembre | C94: =TEXT(CLIENTE[[#This Row],[FECHA]],"YYYY") -> 2020 | D94: 144 | E94: ELEVEMOS S.A.S | F94: =VLOOKUP(CLIENTE[[#This Row],[CLIENTE]],Tabla5[],2,FALSE) -> 900.790.148-4 | G94: 900000 | H94: 0 | I94: =+G94-H94 -> 900000 | J94: 2 LONAS PROTECTORAS ED. RICON DE LA TOJA-ALMENDROS DEL POBLADO | K94: 900000 | L94: =+CLIENTE[[#This Row],[VALOR]]-CLIENTE[[#This Row],[RTE FTE]]-CLIENTE[[#This Row],[Abono]] -> 0
A95: 44109 | B95: =TEXT(CLIENTE[[#This Row],[FECHA]],"MMMM") -> octubre | C95: =TEXT(CLIENTE[[#This Row],[FECHA]],"YYYY") -> 2020 | D95: 145 | E95: EL CHAQUIRO | F95: =VLOOKUP(CLIENTE[[#This Row],[CLIENTE]],Tabla5[],2,FALSE) -> 811.130.040-3 | G95: 520000 | H95: 0 | I95: =+G95-H95 -> 520000 | J95: LONA PROTECTORA ASCENSOR | K95: 520000 | L95: =+CLIENTE[[#This Row],[VALOR]]-CLIENTE[[#This Row],[RTE FTE]]-CLIENTE[[#This Row],[Abono]] -> 0
... A99: 44186 | B99: =TEXT(CLIENTE[[#This Row],[FECHA]],"MMMM") -> diciembre | C99: =TEXT(CLIENTE[[#This Row],[FECHA]],"YYYY") -> 2020 | D99: 149 | E99: EDIFICIO GRAN MEDITERRANEO | F99: =VLOOKUP(CLIENTE[[#This Row],[CLIENTE]],Tabla5[],2,FALSE) -> 800.200.948-7 | G99: 300000 | H99: 18000 | I99: =+G99-H99 -> 282000 | J99: 2 PROTECTORES PARA CARROS DE MERCADO | K99: 282000 | L99: =+CLIENTE[[#This Row],[VALOR]]-CLIENTE[[#This Row],[RTE FTE]]-CLIENTE[[#This Row],[Abono]] -> 0
A100: 44228 | B100: =TEXT(CLIENTE[[#This Row],[FECHA]],"MMMM") -> febrero | C100: =TEXT(CLIENTE[[#This Row],[FECHA]],"YYYY") -> 2021 | D100: 150 | E100: ELEVEMOS S.A.S | F100: =VLOOKUP(CLIENTE[[#This Row],[CLIENTE]],Tabla5[],2,FALSE) -> 900.790.148-4 | G100: 900000 | I100: =+G100-H100 -> 900000 | J100: 1 LONA PROTECTORA RAYO DE SOL-1 LONA ESQUINA DEL CONQUISTADOR | K100: 900000 | L100: =+CLIENTE[[#This Row],[VALOR]]-CLIENTE[[#This Row],[RTE FTE]]-CLIENTE[[#This Row],[Abono]] -> 0
A101: 44233 | B101: =TEXT(CLIENTE[[#This Row],[FECHA]],"MMMM") -> febrero | C101: =TEXT(CLIENTE[[#This Row],[FECHA]],"YYYY") -> 2021 | D101: 151 | E101: EDIFICIO GRAN MEDITERRANEO | F101: =VLOOKUP(CLIENTE[[#This Row],[CLIENTE]],Tabla5[],2,FALSE) -> 800.200.948-7 | G101: 60000 | I101: =+G101-H101 -> 60000 | J101: REFUERZO EN FORROS CARRO DE MERCADOS | K101: 60000 | L101: =+CLIENTE[[#This Row],[VALOR]]-CLIENTE[[#This Row],[RTE FTE]]-CLIENTE[[#This Row],[Abono]] -> 0
A102: 44264 | B102: =TEXT(CLIENTE[[#This Row],[FECHA]],"MMMM") -> marzo | C102: =TEXT(CLIENTE[[#This Row],[FECHA]],"YYYY") -> 2021 | D102: 152 | E102: IMPERIAL ELEVADORES S.A.S | F102: =VLOOKUP(CLIENTE[[#This Row],[CLIENTE]],Tabla5[],2,FALSE) -> 900.828.771-1 | G102: 400000 | I102: =+G102-H102 -> 400000 | J102: 1 LONA PROTECTORA | K102: 400000 | L102: =+CLIENTE[[#This Row],[VALOR]]-CLIENTE[[#This Row],[RTE FTE]]-CLIENTE[[#This Row],[Abono]] -> 0
A103: 44289 | B103: =TEXT(CLIENTE[[#This Row],[FECHA]],"MMMM") -> abril | C103: =TEXT(CLIENTE[[#This Row],[FECHA]],"YYYY") -> 2021 | D103: 153 | E103: ELEVEMOS S.A.S | F103: =VLOOKUP(CLIENTE[[#This Row],[CLIENTE]],Tabla5[],2,FALSE) -> 900.790.148-4 | G103: 450000 | I103: =+G103-H103 -> 450000 | J103: 1 LONA PROTECTORA CEO AGUACATALA | K103: 450000 | L103: =+CLIENTE[[#This Row],[VALOR]]-CLIENTE[[#This Row],[RTE FTE]]-CLIENTE[[#This Row],[Abono]] -> 0
A104: 44289 | B104: =TEXT(CLIENTE[[#This Row],[FECHA]],"MMMM") -> abril | C104: =TEXT(CLIENTE[[#This Row],[FECHA]],"YYYY") -> 2021 | D104: 154 | E104: URBANIZACION VILLAS DE SAN JOSE | F104: =VLOOKUP(CLIENTE[[#This Row],[CLIENTE]],Tabla5[],2,FALSE) -> 800254196 | G104: 940000 | I104: =564000+376000 -> 940000 | J104: CARPA MEDIA NARANJA EN BRIGADIER APT 502 | K104: 940000 | L104: =+CLIENTE[[#This Row],[VALOR]]-CLIENTE[[#This Row],[RTE FTE]]-CLIENTE[[#This Row],[Abono]] -> 0
...

Sheet Hoja1
D1: =+SUM(D2+E2) -> 50841839 | F1: 49850000 | G1: =+D1-F1 -> 991839.21
D2: =+SUM(D4:D7) -> 33461723 | E2: =+SUM(E4:E17) -> 17380117
D3: BANCOLOMBIA | E3: COLPATRIA
D4: 3398207.4 | E4: 3881996.8
D5: 5062172.8 | E5: 1751895.2
D6: 9928014.3 | E6: 2609302.9 | I6: 330000 | J6: 280000
D7: 15073328 | E7: 1680713.5 | H7: =1.35*1.6 -> 2.16 | I7: =+I6*H7 -> 712800 | J7: =+J6*H7 -> 604800
E8: 1681074.7 | H8: =1.25*1.4 -> 1.75 | I8: =+I6*H8 -> 577500 | J8: =+J6*H8 -> 490000
E9: 2823423.4
E10: 2551694.2
E11: 14.7
E12: 0.7
E13: 0.1
E14: 200000.35
E15: 200000

Sheet RESUMEN VENTAS
A2: CONSOLIDADO X AÑOS
A3: VENTAS
B4: TOTALES | C4: =+SUM(Tabla6[2018]) -> 56269560 | D4: =+SUM(Tabla6[2019]) -> 15239000 | E4: =+SUM(Tabla6[2020]) -> 7490000 | F4: =+SUM(Tabla6[2021]) -> 26965000
A5: CLIENTE/AÑO | B5: ACUMULADO | C5: 2018 | D5: 2019 | E5: 2020 | F5: 2021
A6: =B.D!B4 -> ALGAMAR S.A | B6: =+SUMIFS(CLIENTE[VALOR],CLIENTE[CLIENTE],Tabla6[[#This Row],[CLIENTE/AÑO]]) -> 26620000 | C6: =+SUMIFS(CLIENTE[VALOR],CLIENTE[CLIENTE],A6,CLIENTE[AÑO],$C$5) -> 26620000 | D6: =+SUMIFS(CLIENTE[VALOR],CLIENTE[CLIENTE],A6,CLIENTE[AÑO],$D$5) -> 0 | E6: =+SUMIFS(CLIENTE[VALOR],CLIENTE[CLIENTE],A6,CLIENTE[AÑO],$E$5) -> 0 | F6: =+SUMIFS(CLIENTE[VALOR],CLIENTE[CLIENTE],A6,CLIENTE[AÑO],$F$5) -> 0
A7: =B.D!B5 -> HPTU | B7: =+SUMIFS(CLIENTE[VALOR],CLIENTE[CLIENTE],Tabla6[[#This Row],[CLIENTE/AÑO]]) -> 810000 | C7: =+SUMIFS(CLIENTE[VALOR],CLIENTE[CLIENTE],A7,CLIENTE[AÑO],$C$5) -> 810000 | D7: =+SUMIFS(CLIENTE[VALOR],CLIENTE[CLIENTE],A7,CLIENTE[AÑO],$D$5) -> 0 | E7: =+SUMIFS(CLIENTE[VALOR],CLIENTE[CLIENTE],A7,CLIENTE[AÑO],$E$5) -> 0 | F7: =+SUMIFS(CLIENTE[VALOR],CLIENTE[CLIENTE],A7,CLIENTE[AÑO],$F$5) -> 0
A8: =B.D!B6 -> EFITRANS | B8: =+SUMIFS(CLIENTE[VALOR],CLIENTE[CLIENTE],Tabla6[[#This Row],[CLIENTE/AÑO]]) -> 530000 | C8: =+SUMIFS(CLIENTE[VALOR],CLIENTE[CLIENTE],A8,CLIENTE[AÑO],$C$5) -> 530000 | D8: =+SUMIFS(CLIENTE[VALOR],CLIENTE[CLIENTE],A8,CLIENTE[AÑO],$D$5) -> 0 | E8: =+SUMIFS(CLIENTE[VALOR],CLIENTE[CLIENTE],A8,CLIENTE[AÑO],$E$5) -> 0 | F8: =+SUMIFS(CLIENTE[VALOR],CLIENTE[CLIENTE],A8,CLIENTE[AÑO],$F$5) -> 0
A9: =B.D!B7 -> EL TESORO ENTRETENIMIENTO | B9: =+SUMIFS(CLIENTE[VALOR],CLIENTE[CLIENTE],Tabla6[[#This Row],[CLIENTE/AÑO]]) -> 16282360 | C9: =+SUMIFS(CLIENTE[VALOR],CLIENTE[CLIENTE],A9,CLIENTE[AÑO],$C$5) -> 14092360 | D9: =+SUMIFS(CLIENTE[VALOR],CLIENTE[CLIENTE],A9,CLIENTE[AÑO],$D$5) -> 1210000 | E9: =+SUMIFS(CLIENTE[VALOR],CLIENTE[CLIENTE],A9,CLIENTE[AÑO],$E$5) -> 0 | F9: =+SUMIFS(CLIENTE[VALOR],CLIENTE[CLIENTE],A9,CLIENTE[AÑO],$F$5) -> 980000
A10: =B.D!B8 -> REIMPEX S.A | B10: =+SUMIFS(CLIENTE[VALOR],CLIENTE[CLIENTE],Tabla6[[#This Row],[CLIENTE/AÑO]]) -> 775000 | D10: =+SUMIFS(CLIENTE[VALOR],CLIENTE[CLIENTE],A10,CLIENTE[AÑO],$D$5) -> 405000 | E10: =+SUMIFS(CLIENTE[VALOR],CLIENTE[CLIENTE],A10,CLIENTE[AÑO],$E$5) -> 0 | F10: =+SUMIFS(CLIENTE[VALOR],CLIENTE[CLIENTE],A10,CLIENTE[AÑO],$F$5) -> 0
A11: =B.D!B9 -> URBANIZACION SAINT PIERRE P.H | B11: =+SUMIFS(CLIENTE[VALOR],CLIENTE[CLIENTE],Tabla6[[#This Row],[CLIENTE/AÑO]]) -> 367200 | C11: =+SUMIFS(CLIENTE[VALOR],CLIENTE[CLIENTE],A11,CLIENTE[AÑO],$C$5) -> 367200 | D11: =+SUMIFS(CLIENTE[VALOR],CLIENTE[CLIENTE],A11,CLIENTE[AÑO],$D$5) -> 0 | E11: =+SUMIFS(CLIENTE[VALOR],CLIENTE[CLIENTE],A11,CLIENTE[AÑO],$E$5) -> 0 | F11: =+SUMIFS(CLIENTE[VALOR],CLIENTE[CLIENTE],A11,CLIENTE[AÑO],$F$5) -> 0
A12: =B.D!B10 -> URBANIZACION SAINT MARTEEN P.H | B12: =+SUMIFS(CLIENTE[VALOR],CLIENTE[CLIENTE],Tabla6[[#This Row],[CLIENTE/AÑO]]) -> 350000 | C12: =+SUMIFS(CLIENTE[VALOR],CLIENTE[CLIENTE],A12,CLIENTE[AÑO],$C$5) -> 350000 | D12: =+SUMIFS(CLIENTE[VALOR],CLIENTE[CLIENTE],A12,CLIENTE[AÑO],$D$5) -> 0 | E12: =+SUMIFS(CLIENTE[VALOR],CLIENTE[CLIENTE],A12,CLIENTE[AÑO],$E$5) -> 0 | F12: =+SUMIFS(CLIENTE[VALOR],CLIENTE[CLIENTE],A12,CLIENTE[AÑO],$F$5) -> 0
A13: =B.D!B11 -> HECKCACOL SERVICIOS INDUSTRIALES S.A.S | B13: =+SUMIFS(CLIENTE[VALOR],CLIENTE[CLIENTE],Tabla6[[#This Row],[CLIENTE/AÑO]]) -> 1280000 | C13: =+SUMIFS(CLIENTE[VALOR],CLIENTE[CLIENTE],A13,CLIENTE[AÑO],$C$5) -> 650000 | D13: =+SUMIFS(CLIENTE[VALOR],CLIENTE[CLIENTE],A13,CLIENTE[AÑO],$D$5) -> 0 | E13: =+SUMIFS(CLIENTE[VALOR],CLIENTE[CLIENTE],A13,CLIENTE[AÑO],$E$5) -> 630000 | F13: =+SUMIFS(CLIENTE[VALOR],CLIENTE[CLIENTE],A13,CLIENTE[AÑO],$F$5) -> 0
A14: =B.D!B12 -> PLATAFORMA LOGISTICA Y COMERCIAL S.A.S | B14: =+SUMIFS(CLIENTE[VALOR],CLIENTE[CLIENTE],Tabla6[[#This Row],[CLIENTE/AÑO]]) -> 22104000 | C14: =+SUMIFS(CLIENTE[VALOR],CLIENTE[CLIENTE],A14,CLIENTE[AÑO],$C$5) -> 9600000 | D14: =+SUMIFS(CLIENTE[VALOR],CLIENTE[CLIENTE],A14,CLIENTE[AÑO],$D$5) -> 12504000 | E14: =+SUMIFS(CLIENTE[VALOR],CLIENTE[CLIENTE],A14,CLIENTE[AÑO],$E$5) -> 0 | F14: =+SUMIFS(CLIENTE[VALOR],CLIENTE[CLIENTE],A14,CLIENTE[AÑO],$F$5) -> 0
A15: =B.D!B13 -> RISKS & PROTECTION LTDA | B15: =+SUMIFS(CLIENTE[VALOR],CLIENTE[CLIENTE],Tabla6[[#This Row],[CLIENTE/AÑO]]) -> 350000 | C15: =+SUMIFS(CLIENTE[VALOR],CLIENTE[CLIENTE],A15,CLIENTE[AÑO],$C$5) -> 350000 | D15: =+SUMIFS(CLIENTE[VALOR],CLIENTE[CLIENTE],A15,CLIENTE[AÑO],$D$5) -> 0 | E15: =+SUMIFS(CLIENTE[VALOR],CLIENTE[CLIENTE],A15,CLIENTE[AÑO],$E$5) -> 0 | F15: =+SUMIFS(CLIENTE[VALOR],CLIENTE[CLIENTE],A15,CLIENTE[AÑO],$F$5) -> 0
A16: =B.D!B14 -> CARLOS MARIO MOLINA V | B16: =+SUMIFS(CLIENTE[VALOR],CLIENTE[CLIENTE],Tabla6[[#This Row],[CLIENTE/AÑO]]) -> 800000 | C16: =+SUMIFS(CLIENTE[VALOR],CLIENTE[CLIENTE],A16,CLIENTE[AÑO],$C$5) -> 800000 | D16: =+SUMIFS(CLIENTE[VALOR],CLIENTE[CLIENTE],A16,CLIENTE[AÑO],$D$5) -> 0 | E16: =+SUMIFS(CLIENTE[VALOR],CLIENTE[CLIENTE],A16,CLIENTE[AÑO],$E$5) -> 0 | F16: =+SUMIFS(CLIENTE[VALOR],CLIENTE[CLIENTE],A16,CLIENTE[AÑO],$F$5) -> 0
A17: =B.D!B15 -> EFITRANS S.A.S | B17: =+SUMIFS(CLIENTE[VALOR],CLIENTE[CLIENTE],Tabla6[[#This Row],[CLIENTE/AÑO]]) -> 820000 | C17: =+SUMIFS(CLIENTE[VALOR],CLIENTE[CLIENTE],A17,CLIENTE[AÑO],$C$5) -> 0 | D17: =+SUMIFS(CLIENTE[VALOR],CLIENTE[CLIENTE],A17,CLIENTE[AÑO],$D$5) -> 820000 | E17: =+SUMIFS(CLIENTE[VALOR],CLIENTE[CLIENTE],A17,CLIENTE[AÑO],$E$5) -> 0 | F17: =+SUMIFS(CLIENTE[VALOR],CLIENTE[CLIENTE],A17,CLIENTE[AÑO],$F$5) -> 0
A18: =B.D!B16 -> SINTRABANCOL | B18: =+SUMIFS(CLIENTE[VALOR],CLIENTE[CLIENTE],Tabla6[[#This Row],[CLIENTE/AÑO]]) -> 185000 | D18: =+SUMIFS(CLIENTE[VALOR],CLIENTE[CLIENTE],A18,CLIENTE[AÑO],$D$5) -> 0 | E18: =+SUMIFS(CLIENTE[VALOR],CLIENTE[CLIENTE],A18,CLIENTE[AÑO],$E$5) -> 0 | F18: =+SUMIFS(CLIENTE[VALOR],CLIENTE[CLIENTE],A18,CLIENTE[AÑO],$F$5) -> 0
A19: =B.D!B17 -> FIJACIONES OROZCO S.A.S | B19: =+SUMIFS(CLIENTE[VALOR],CLIENTE[CLIENTE],Tabla6[[#This Row],[CLIENTE/AÑO]]) -> 100000 | C19: =+SUMIFS(CLIENTE[VALOR],CLIENTE[CLIENTE],A19,CLIENTE[AÑO],$C$5) -> 100000 | D19: =+SUMIFS(CLIENTE[VALOR],CLIENTE[CLIENTE],A19,CLIENTE[AÑO],$D$5) -> 0 | E19: =+SUMIFS(CLIENTE[VALOR],CLIENTE[CLIENTE],A19,CLIENTE[AÑO],$E$5) -> 0 | F19: =+SUMIFS(CLIENTE[VALOR],CLIENTE[CLIENTE],A19,CLIENTE[AÑO],$F$5) -> 0
A20: =B.D!B18 -> GABRIEL ARTURO ALZATE | B20: =+SUMIFS(CLIENTE[VALOR],CLIENTE[CLIENTE],Tabla6[[#This Row],[CLIENTE/AÑO]]) -> 2000000 | C20: =+SUMIFS(CLIENTE[VALOR],CLIENTE[CLIENTE],A20,CLIENTE[AÑO],$C$5) -> 2000000 | D20: =+SUMIFS(CLIENTE[VALOR],CLIENTE[CLIENTE],A20,CLIENTE[AÑO],$D$5) -> 0 | E20: =+SUMIFS(CLIENTE[VALOR],CLIENTE[CLIENTE],A20,CLIENTE[AÑO],$E$5) -> 0 | F20: =+SUMIFS(CLIENTE[VALOR],CLIENTE[CLIENTE],A20,CLIENTE[AÑO],$F$5) -> 0
A21: =B.D!B19 -> CENTRO MEDICO VETERINARIO BELLOS CANES | B21: =+SUMIFS(CLIENTE[VALOR],CLIENTE[CLIENTE],Tabla6[[#This Row],[CLIENTE/AÑO]]) -> 30000 | C21: =+SUMIFS(CLIENTE[VALOR],CLIENTE[CLIENTE],A21,CLIENTE[AÑO],$C$5) -> 0 | D21: =+SUMIFS(CLIENTE[VALOR],CLIENTE[CLIENTE],A21,CLIENTE[AÑO],$D$5) -> 30000 | E21: =+SUMIFS(CLIENTE[VALOR],CLIENTE[CLIENTE],A21,CLIENTE[AÑO],$E$5) -> 0 | F21: =+SUMIFS(CLIENTE[VALOR],CLIENTE[CLIENTE],A21,CLIENTE[AÑO],$F$5) -> 0
A22: =B.D!B20 -> INGENIERIA EFICIENTE DEL AIRE S.A.S | B22: =+SUMIFS(CLIENTE[VALOR],CLIENTE[CLIENTE],Tabla6[[#This Row],[CLIENTE/AÑO]]) -> 270000 | D22: =+SUMIFS(CLIENTE[VALOR],CLIENTE[CLIENTE],A22,CLIENTE[AÑO],$D$5) -> 270000 | E22: =+SUMIFS(CLIENTE[VALOR],CLIENTE[CLIENTE],A22,CLIENTE[AÑO],$E$5) -> 0 | F22: =+SUMIFS(CLIENTE[VALOR],CLIENTE[CLIENTE],A22,CLIENTE[AÑO],$F$5) -> 0
A23: =B.D!B21 -> ELEVEMOS S.A.S | B23: =+SUMIFS(CLIENTE[VALOR],CLIENTE[CLIENTE],Tabla6[[#This Row],[CLIENTE/AÑO]]) -> 7628000 | C23: =+SUMIFS(CLIENTE[VALOR],CLIENTE[CLIENTE],A23,CLIENTE[AÑO],$C$5) -> 0 | D23: =+SUMIFS(CLIENTE[VALOR],CLIENTE[CLIENTE],A23,CLIENTE[AÑO],$D$5) -> 0 | E23: =+SUMIFS(CLIENTE[VALOR],CLIENTE[CLIENTE],A23,CLIENTE[AÑO],$E$5) -> 3988000 | F23: =+SUMIFS(CLIENTE[VALOR],CLIENTE[CLIENTE],A23,CLIENTE[AÑO],$F$5) -> 2760000
A24: =B.D!B22 -> PROELECTRA DE COLOMBIA S.A.S | B24: =+SUMIFS(CLIENTE[VALOR],CLIENTE[CLIENTE],Tabla6[[#This Row],[CLIENTE/AÑO]]) -> 671000 | C24: =+SUMIFS(CLIENTE[VALOR],CLIENTE[CLIENTE],A24,CLIENTE[AÑO],$C$5) -> 0 | D24: =+SUMIFS(CLIENTE[VALOR],CLIENTE[CLIENTE],A24,CLIENTE[AÑO],$D$5) -> 0 | E24: =+SUMIFS(CLIENTE[VALOR],CLIENTE[CLIENTE],A24,CLIENTE[AÑO],$E$5) -> 386000 | F24: =+SUMIFS(CLIENTE[VALOR],CLIENTE[CLIENTE],A24,CLIENTE[AÑO],$F$5) -> 285000
A25: =B.D!B23 -> EL CHAQUIRO | B25: =+SUMIFS(CLIENTE[VALOR],CLIENTE[CLIENTE],Tabla6[[#This Row],[CLIENTE/AÑO]]) -> 520000 | C25: =+SUMIFS(CLIENTE[VALOR],CLIENTE[CLIENTE],A25,CLIENTE[AÑO],$C$5) -> 0 | D25: =+SUMIFS(CLIENTE[VALOR],CLIENTE[CLIENTE],A25,CLIENTE[AÑO],$D$5) -> 0 | E25: =+SUMIFS(CLIENTE[VALOR],CLIENTE[CLIENTE],A25,CLIENTE[AÑO],$E$5) -> 520000 | F25: =+SUMIFS(CLIENTE[VALOR],CLIENTE[CLIENTE],A25,CLIENTE[AÑO],$F$5) -> 0
A26: =B.D!B24 -> URBANIZACION ALTOS DEL POBLADO 1 P.H | B26: =+SUMIFS(CLIENTE[VALOR],CLIENTE[CLIENTE],Tabla6[[#This Row],[CLIENTE/AÑO]]) -> 550000 | C26: =+SUMIFS(CLIENTE[VALOR],CLIENTE[CLIENTE],A26,CLIENTE[AÑO],$C$5) -> 0 | D26: =+SUMIFS(CLIENTE[VALOR],CLIENTE[CLIENTE],A26,CLIENTE[AÑO],$D$5) -> 0 | E26: =+SUMIFS(CLIENTE[VALOR],CLIENTE[CLIENTE],A26,CLIENTE[AÑO],$E$5) -> 550000 | F26: =+SUMIFS(CLIENTE[VALOR],CLIENTE[CLIENTE],A26,CLIENTE[AÑO],$F$5) -> 0
A27: =B.D!B25 -> EDIFICIO GRAN MEDITERRANEO | B27: =+SUMIFS(CLIENTE[VALOR],CLIENTE[CLIENTE],Tabla6[[#This Row],[CLIENTE/AÑO]]) -> 360000 | C27: =+SUMIFS(CLIENTE[VALOR],CLIENTE[CLIENTE],A27,CLIENTE[AÑO],$C$5) -> 0 | D27: =+SUMIFS(CLIENTE[VALOR],CLIENTE[CLIENTE],A27,CLIENTE[AÑO],$D$5) -> 0 | E27: =+SUMIFS(CLIENTE[VALOR],CLIENTE[CLIENTE],A27,CLIENTE[AÑO],$E$5) -> 300000 | F27: =+SUMIFS(CLIENTE[VALOR],CLIENTE[CLIENTE],A27,CLIENTE[AÑO],$F$5) -> 60000
A28: =B.D!B26 -> TRANSPORTE Y TURISMO 1A S.A.S | B28: =+SUMIFS(CLIENTE[VALOR],CLIENTE[CLIENTE],Tabla6[[#This Row],[CLIENTE/AÑO]]) -> 396000 | C28: =+SUMIFS(CLIENTE[VALOR],CLIENTE[CLIENTE],A28,CLIENTE[AÑO],$C$5) -> 0 | D28: =+SUMIFS(CLIENTE[VALOR],CLIENTE[CLIENTE],A28,CLIENTE[AÑO],$D$5) -> 0 | E28: =+SUMIFS(CLIENTE[VALOR],CLIENTE[CLIENTE],A28,CLIENTE[AÑO],$E$5) -> 396000 | F28: =+SUMIFS(CLIENTE[VALOR],CLIENTE[CLIENTE],A28,CLIENTE[AÑO],$F$5) -> 0
A29: =B.D!B27 -> CONJUNTO RESIDENCIAL PALOS DE MOGUER | B29: =+SUMIFS(CLIENTE[VALOR],CLIENTE[CLIENTE],Tabla6[[#This Row],[CLIENTE/AÑO]]) -> 720000 | C29: =+SUMIFS(CLIENTE[VALOR],CLIENTE[CLIENTE],A29,CLIENTE[AÑO],$C$5) -> 0 | D29: =+SUMIFS(CLIENTE[VALOR],CLIENTE[CLIENTE],A29,CLIENTE[AÑO],$D$5) -> 0 | E29: =+SUMIFS(CLIENTE[VALOR],CLIENTE[CLIENTE],A29,CLIENTE[AÑO],$E$5) -> 720000 | F29: =+SUMIFS(CLIENTE[VALOR],CLIENTE[CLIENTE],A29,CLIENTE[AÑO],$F$5) -> 0
A30: =B.D!B28 -> IMPERIAL ELEVADORES S.A.S | B30: =+SUMIFS(CLIENTE[VALOR],CLIENTE[CLIENTE],Tabla6[[#This Row],[CLIENTE/AÑO]]) -> 2060000 | C30: =+SUMIFS(CLIENTE[VALOR],CLIENTE[CLIENTE],A30,CLIENTE[AÑO],$C$5) -> 0 | D30: =+SUMIFS(CLIENTE[VALOR],CLIENTE[CLIENTE],A30,CLIENTE[AÑO],$D$5) -> 0 | E30: =+SUMIFS(CLIENTE[VALOR],CLIENTE[CLIENTE],A30,CLIENTE[AÑO],$E$5) -> 0 | F30: =+SUMIFS(CLIENTE[VALOR],CLIENTE[CLIENTE],A30,CLIENTE[AÑO],$F$5) -> 2060000
A31: =B.D!B29 -> URBANIZACION VILLAS DE SAN JOSE | B31: =+SUMIFS(CLIENTE[VALOR],CLIENTE[CLIENTE],Tabla6[[#This Row],[CLIENTE/AÑO]]) -> 940000 | C31: =+SUMIFS(CLIENTE[VALOR],CLIENTE[CLIENTE],A31,CLIENTE[AÑO],$C$5) -> 0 | D31: =+SUMIFS(CLIENTE[VALOR],CLIENTE[CLIENTE],A31,CLIENTE[AÑO],$D$5) -> 0 | E31: =+SUMIFS(CLIENTE[VALOR],CLIENTE[CLIENTE],A31,CLIENTE[AÑO],$E$5) -> 0 | F31: =+SUMIFS(CLIENTE[VALOR],CLIENTE[CLIENTE],A31,CLIENTE[AÑO],$F$5) -> 940000
A32: =B.D!B30 -> FULL ZONE S.A.S | B32: =+SUMIFS(CLIENTE[VALOR],CLIENTE[CLIENTE],Tabla6[[#This Row],[CLIENTE/AÑO]]) -> 11000000 | C32: =+SUMIFS(CLIENTE[VALOR],CLIENTE[CLIENTE],A32,CLIENTE[AÑO],$C$5) -> 0 | D32: =+SUMIFS(CLIENTE[VALOR],CLIENTE[CLIENTE],A32,CLIENTE[AÑO],$D$5) -> 0 | E32: =+SUMIFS(CLIENTE[VALOR],CLIENTE[CLIENTE],A32,CLIENTE[AÑO],$E$5) -> 0 | F32: =+SUMIFS(CLIENTE[VALOR],CLIENTE[CLIENTE],A32,CLIENTE[AÑO],$F$5) -> 11000000
A33: =B.D!B31 -> EDIFICIO BASILEA | B33: =+SUMIFS(CLIENTE[VALOR],CLIENTE[CLIENTE],Tabla6[[#This Row],[CLIENTE/AÑO]]) -> 600000 | C33: =+SUMIFS(CLIENTE[VALOR],CLIENTE[CLIENTE],A33,CLIENTE[AÑO],$C$5) -> 0 | D33: =+SUMIFS(CLIENTE[VALOR],CLIENTE[CLIENTE],A33,CLIENTE[AÑO],$D$5) -> 0 | E33: =+SUMIFS(CLIENTE[VALOR],CLIENTE[CLIENTE],A33,CLIENTE[AÑO],$E$5) -> 0 | F33: =+SUMIFS(CLIENTE[VALOR],CLIENTE[CLIENTE],A33,CLIENTE[AÑO],$F$5) -> 600000
A34: =B.D!B32 -> C.R TORRES DEL CASTILLO | B34: =+SUMIFS(CLIENTE[VALOR],CLIENTE[CLIENTE],Tabla6[[#This Row],[CLIENTE/AÑO]]) -> 500000 | C34: =+SUMIFS(CLIENTE[VALOR],CLIENTE[CLIENTE],A34,CLIENTE[AÑO],$C$5) -> 0 | D34: =+SUMIFS(CLIENTE[VALOR],CLIENTE[CLIENTE],A34,CLIENTE[AÑO],$D$5) -> 0 | E34: =+SUMIFS(CLIENTE[VALOR],CLIENTE[CLIENTE],A34,CLIENTE[AÑO],$E$5) -> 0 | F34: =+SUMIFS(CLIENTE[VALOR],CLIENTE[CLIENTE],A34,CLIENTE[AÑO],$F$5) -> 500000
... A47: =B.D!B45 -> 0 | B47: =+SUMIFS(CLIENTE[VALOR],CLIENTE[CLIENTE],Tabla6[[#This Row],[CLIENTE/AÑO]]) -> 0 | C47: =+SUMIFS(CLIENTE[VALOR],CLIENTE[CLIENTE],A47,CLIENTE[AÑO],$C$5) -> 0 | D47: =+SUMIFS(CLIENTE[VALOR],CLIENTE[CLIENTE],A47,CLIENTE[AÑO],$D$5) -> 0 | E47: =+SUMIFS(CLIENTE[VALOR],CLIENTE[CLIENTE],A47,CLIENTE[AÑO],$E$5) -> 0 | F47: =+SUMIFS(CLIENTE[VALOR],CLIENTE[CLIENTE],A47,CLIENTE[AÑO],$F$5) -> 0

Sheet COMPRAS
A1: COMPRAS JOSE ANDRES CORTES | N1: TOTAL COMPRAS | O1: =+SUM(I4:I500) -> 6037752.7
A2: 2018 | N2: TOTAL IVA | O2: =+SUM(H4:H500) -> 866277.2
A3: FECHA | B3: MES | C3: AÑO | D3: FACTURA | E3: PROVEEDOR | F3: NIT | G3: VALOR | H3: IVA | I3: TOTAL | J3: DESCRIPCION
A4: 43146 | B4: =+TEXT(Tabla1[[#This Row],[FECHA]],"MMMM") -> febrero | C4: =+TEXT(Tabla1[[#This Row],[FECHA]],"AAAA") -> jueves | D4: 16388 | E4: INDUSTRIAS JB S.A.S | F4: =+VLOOKUP(Tabla1[[#This Row],[PROVEEDOR]],Tabla7[],2,FALSE) -> 890.923.680-0 | G4: 268908 | H4: =+G4*19% -> 51092.52 | I4: =+G4+H4 -> 320000.52 | J4: CAMBIO DE MOFLE CAMIONETA
A5: 43210 | B5: =+TEXT(Tabla1[[#This Row],[FECHA]],"MMMM") -> abril | C5: =+TEXT(Tabla1[[#This Row],[FECHA]],"AAAA") -> viernes | D5: 264168 | E5: LUZ MARINA PAMPLONA | F5: =+VLOOKUP(Tabla1[[#This Row],[PROVEEDOR]],Tabla7[],2,FALSE) -> 42.765.696-1 | G5: 8403.36 | H5: =+G5*19% -> 1596.6384 | I5: =+G5+H5 -> 9999.9984 | J5: GRAPA
A6: 43214 | B6: =+TEXT(Tabla1[[#This Row],[FECHA]],"MMMM") -> abril | C6: =+TEXT(Tabla1[[#This Row],[FECHA]],"AAAA") -> martes | D6: 264603 | E6: LUZ MARINA PAMPLONA | F6: =+VLOOKUP(Tabla1[[#This Row],[PROVEEDOR]],Tabla7[],2,FALSE) -> 42.765.696-1 | G6: 3361.34 | H6: =+G6*19% -> 638.6546 | I6: =+G6+H6 -> 3999.9946 | J6: THINNER
A7: 43215 | B7: =+TEXT(Tabla1[[#This Row],[FECHA]],"MMMM") -> abril | C7: =+TEXT(Tabla1[[#This Row],[FECHA]],"AAAA") -> miércoles | D7: 20227 | E7: ESPINTURAS S.A.S | F7: =+VLOOKUP(Tabla1[[#This Row],[PROVEEDOR]],Tabla7[],2,FALSE) -> 900.113.676-9 | G7: 42016.9 | H7: =+G7*19% -> 7983.211 | I7: =+G7+H7 -> 50000.111 | J7: VINILTEX PLASTEL
A8: 43229 | B8: =+TEXT(Tabla1[[#This Row],[FECHA]],"MMMM") -> mayo | C8: =+TEXT(Tabla1[[#This Row],[FECHA]],"AAAA") -> miércoles | D8: 77085 | E8: PRODUCTOS COPLAST | F8: =+VLOOKUP(Tabla1[[#This Row],[PROVEEDOR]],Tabla7[],2,FALSE) -> 890.928.831-7 | G8: 23529 | H8: =+G8*19% -> 4470.51 | I8: =+G8+H8 -> 27999.51 | J8: 20 BOLSAS PLASTICAS 110X70
A9: 43238 | B9: =+TEXT(Tabla1[[#This Row],[FECHA]],"MMMM") -> mayo | C9: =+TEXT(Tabla1[[#This Row],[FECHA]],"AAAA") -> viernes | D9: 890069 | E9: CENCOSUD COLOMBIA S.A | F9: =+VLOOKUP(Tabla1[[#This Row],[PROVEEDOR]],Tabla7[],2,FALSE) -> 900.155.107-1 | G9: 18441 | H9: =+G9*19% -> 3503.79 | I9: =+G9+H9 -> 21944.79 | J9: PAÑO-LLANTAX
A10: 43241 | B10: =+TEXT(Tabla1[[#This Row],[FECHA]],"MMMM") -> mayo | C10: =+TEXT(Tabla1[[#This Row],[FECHA]],"AAAA") -> lunes | D10: 1383 | E10: COMERCIALIZADORA CALYPSO S.A.S | F10: =+VLOOKUP(Tabla1[[#This Row],[PROVEEDOR]],Tabla7[],2,FALSE) -> 860.075.208-7 | G10: 11176 | H10: =+G10*19% -> 2123.44 | I10: =+G10+H10 -> 13299.44 | J10: PEGANTE 689
A11: 43242 | B11: =+TEXT(Tabla1[[#This Row],[FECHA]],"MMMM") -> mayo | C11: =+TEXT(Tabla1[[#This Row],[FECHA]],"AAAA") -> martes | D11: 81667 | E11: PC CHAMPION S.A.S | F11: =+VLOOKUP(Tabla1[[#This Row],[PROVEEDOR]],Tabla7[],2,FALSE) -> 830.022.380-1 | G11: 14370 | H11: =+G11*19% -> 2730.3 | I11: =+G11+H11 -> 17100.3 | J11: 1/4 ACEITE 20W50
A12: 43243 | B12: =+TEXT(Tabla1[[#This Row],[FECHA]],"MMMM") -> mayo | C12: =+TEXT(Tabla1[[#This Row],[FECHA]],"AAAA") -> miércoles | D12: 3993 | E12: AREA TUNNING LUJOS Y SONIDOS S.A.S | F12: =+VLOOKUP(Tabla1[[#This Row],[PROVEEDOR]],Tabla7[],2,FALSE) -> 0 | G12: 43697 | H12: =+G12*19% -> 8302.43 | I12: =+G12+H12 -> 51999.43 | J12: BOMBILLOS
A13: 43272 | B13: =+TEXT(Tabla1[[#This Row],[FECHA]],"MMMM") -> junio | C13: =+TEXT(Tabla1[[#This Row],[FECHA]],"AAAA") -> jueves | D13: 1620 | E13: COMERCIALIZADORA CALYPSO S.A.S | F13: =+VLOOKUP(Tabla1[[#This Row],[PROVEEDOR]],Tabla7[],2,FALSE) -> 860.075.208-7 | G13: 59134 | H13: =+G13*19% -> 11235.46 | I13: =+G13+H13 -> 70369.46 | J13: 3.1 LONA ESPAÑA GRIS
A14: 43278 | B14: =+TEXT(Tabla1[[#This Row],[FECHA]],"MMMM") -> junio | C14: =+TEXT(Tabla1[[#This Row],[FECHA]],"AAAA") -> miércoles | D14: 63100 | E14: CENTRO DE SERVICIOS BELLO S.A.S. | F14: =+VLOOKUP(Tabla1[[#This Row],[PROVEEDOR]],Tabla7[],2,FALSE) -> 811.000.785-5 | G14: 133511 | H14: =+G14*19% -> 25367.09 | I14: =+G14+H14+33422 -> 192300.09 | J14: CDA MNV811
A15: 43304 | B15: =+TEXT(Tabla1[[#This Row],[FECHA]],"MMMM") -> julio | C15: =+TEXT(Tabla1[[#This Row],[FECHA]],"AAAA") -> lunes | D15: 29661 | E15: ANDRES FERNEY PUERTA | F15: =+VLOOKUP(Tabla1[[#This Row],[PROVEEDOR]],Tabla7[],2,FALSE) -> 71.212.993-7 | G15: 19328 | H15: =+G15*19% -> 3672.32 | I15: =+G15+H15 -> 23000.32 | J15: ELECTRICOS
A16: 43306 | B16: =+TEXT(Tabla1[[#This Row],[FECHA]],"MMMM") -> julio | C16: =+TEXT(Tabla1[[#This Row],[FECHA]],"AAAA") -> miércoles | D16: 299808 | E16: ANDRES FERNEY PUERTA | F16: =+VLOOKUP(Tabla1[[#This Row],[PROVEEDOR]],Tabla7[],2,FALSE) -> 71.212.993-7 | G16: 8151 | H16: =+G16*19% -> 1548.69 | I16: =+G16+H16 -> 9699.69 | J16: ELECTRICOS
A17: 43306 | B17: =+TEXT(Tabla1[[#This Row],[FECHA]],"MMMM") -> julio | C17: =+TEXT(Tabla1[[#This Row],[FECHA]],"AAAA") -> miércoles | D17: 4875 | E17: COMERCIALIZADORA CALYPSO S.A.S | F17: =+VLOOKUP(Tabla1[[#This Row],[PROVEEDOR]],Tabla7[],2,FALSE) -> 860.075.208-7 | G17: 10504 | H17: =+G17*19% -> 1995.76 | I17: =+G17+H17 -> 12499.76 | J17: PEGANTE 689
A18: 43313 | B18: =+TEXT(Tabla1[[#This Row],[FECHA]],"MMMM") -> agosto | C18: =+TEXT(Tabla1[[#This Row],[FECHA]],"AAAA") -> miércoles | D18: 58265 | E18: FERROSVEL S.A.S | F18: =+VLOOKUP(Tabla1[[#This Row],[PROVEEDOR]],Tabla7[],2,FALSE) -> 890.910.715-1 | G18: 43656 | H18: =+G18*19% -> 8294.64 | I18: =+G18+H18 -> 51950.64 | J18: TUBO CUAD 40X40X2
A19: 43318 | B19: =+TEXT(Tabla1[[#This Row],[FECHA]],"MMMM") -> agosto | C19: =+TEXT(Tabla1[[#This Row],[FECHA]],"AAAA") -> lunes | D19: 42013486 | E19: SODIMAC COLOMBIA | F19: =+VLOOKUP(Tabla1[[#This Row],[PROVEEDOR]],Tabla7[],2,FALSE) -> 800.242.106-2 | G19: 204706 | H19: =+G19*19% -> 38894.14 | I19: =+G19+H19 -> 243600.14 | J19: PISTOLA SOPLADORA
A20: 43327 | B20: =+TEXT(Tabla1[[#This Row],[FECHA]],"MMMM") -> agosto | C20: =+TEXT(Tabla1[[#This Row],[FECHA]],"AAAA") -> miércoles | D20: 78336 | E20: PRODUCTOS COPLAST | F20: =+VLOOKUP(Tabla1[[#This Row],[PROVEEDOR]],Tabla7[],2,FALSE) -> 890.928.831-7 | G20: 23529 | H20: =+G20*19% -> 4470.51 | I20: =+G20+H20 -> 27999.51 | J20: 20 BOLSAS PLASTICAS 110X70
A21: 43327 | B21: =+TEXT(Tabla1[[#This Row],[FECHA]],"MMMM") -> agosto | C21: =+TEXT(Tabla1[[#This Row],[FECHA]],"AAAA") -> miércoles | D21: 105562 | E21: JUAN F. ESTRADA | F21: =+VLOOKUP(Tabla1[[#This Row],[PROVEEDOR]],Tabla7[],2,FALSE) -> 71.315.681-7 | G21: 11176 | H21: =+G21*19% -> 2123.44 | I21: =+G21+H21 -> 13299.44 | J21: MEDIA ARGOLLA
A22: 43328 | B22: =+TEXT(Tabla1[[#This Row],[FECHA]],"MMMM") -> agosto | C22: =+TEXT(Tabla1[[#This Row],[FECHA]],"AAAA") -> jueves | D22: 55390 | E22: ALMACENES CORONA S.A.S | F22: =+VLOOKUP(Tabla1[[#This Row],[PROVEEDOR]],Tabla7[],2,FALSE) -> 860.500.480-8 | G22: =85827.74-2100.84 -> 83726.9 | H22: =+G22*19% -> 15908.111 | I22: =+G22+H22 -> 99635.011 | J22: PEGACOR-LISTON-PARED NEGRO
A23: 43328 | B23: =+TEXT(Tabla1[[#This Row],[FECHA]],"MMMM") -> agosto | C23: =+TEXT(Tabla1[[#This Row],[FECHA]],"AAAA") -> jueves | D23: 61526 | E23: MATERIALES SU CONSTRUCCION S.A | F23: =+VLOOKUP(Tabla1[[#This Row],[PROVEEDOR]],Tabla7[],2,FALSE) -> 800.147.650-1 | G23: 18877 | H23: =+G23*19% -> 3586.63 | I23: =+G23+H23 -> 22463.63 | J23: SIFON-CANASTILLA
A24: 43330 | B24: =+TEXT(Tabla1[[#This Row],[FECHA]],"MMMM") -> agosto | C24: =+TEXT(Tabla1[[#This Row],[FECHA]],"AAAA") -> sábado | D24: 276971 | E24: LUZ MARINA PAMPLONA | F24: =+VLOOKUP(Tabla1[[#This Row],[PROVEEDOR]],Tabla7[],2,FALSE) -> 42.765.696-1 | G24: 2689.08 | H24: =+G24*19% -> 510.9252 | I24: =+G24+H24 -> 3200.0052 | J24: LECHADA BLANCA
A25: 43334 | B25: =+TEXT(Tabla1[[#This Row],[FECHA]],"MMMM") -> agosto | C25: =+TEXT(Tabla1[[#This Row],[FECHA]],"AAAA") -> miércoles | D25: 2947 | E25: AUTOLATAS S.A.S | F25: =+VLOOKUP(Tabla1[[#This Row],[PROVEEDOR]],Tabla7[],2,FALSE) -> 901.165.210-7 | G25: =36414-3641 -> 32773 | H25: =+G25*19% -> 6226.87 | I25: =+G25+H25 -> 38999.87 | J25: ARO DER. MAZDA
A26: 43206 | B26: =+TEXT(Tabla1[[#This Row],[FECHA]],"MMMM") -> abril | C26: =+TEXT(Tabla1[[#This Row],[FECHA]],"AAAA") -> lunes | D26: 55598 | E26: MATERIALES EL TITAN 1 S.A.S | F26: =+VLOOKUP(Tabla1[[#This Row],[PROVEEDOR]],Tabla7[],2,FALSE) -> 811.023.960-7 | G26: 75600 | H26: 0 | I26: =+G26+H26 -> 75600 | J26: BLOQUELON
A27: 43209 | B27: =+TEXT(Tabla1[[#This Row],[FECHA]],"MMMM") -> abril | C27: =+TEXT(Tabla1[[#This Row],[FECHA]],"AAAA") -> jueves | D27: 11791 | E27: J&J ASOCIADOS | F27: =+VLOOKUP(Tabla1[[#This Row],[PROVEEDOR]],Tabla7[],2,FALSE) -> 811.047.183-4 | G27: 23138 | H27: =+G27*19% -> 4396.22 | I27: =+G27+H27 -> 27534.22 | J27: 2 GRUESAS DE OJALETES 5/8
A28: 43154 | B28: =+TEXT(Tabla1[[#This Row],[FECHA]],"MMMM") -> febrero | C28: =+TEXT(Tabla1[[#This Row],[FECHA]],"AAAA") -> viernes | D28: 109044 | E28: COMERCIALIZADORA CALYPSO S.A.S | F28: =+VLOOKUP(Tabla1[[#This Row],[PROVEEDOR]],Tabla7[],2,FALSE) -> 860.075.208-7 | G28: 100252.09 | H28: =+G28*19% -> 19047.897 | I28: =+G28+H28 -> 119299.99 | J28: 5.3 LONA ESPAÑA AZUL
A29: 43175 | B29: =+TEXT(Tabla1[[#This Row],[FECHA]],"MMMM") -> marzo | C29: =+TEXT(Tabla1[[#This Row],[FECHA]],"AAAA") -> viernes | D29: 19754 | E29: ESPINTURAS S.A.S | F29: =+VLOOKUP(Tabla1[[#This Row],[PROVEEDOR]],Tabla7[],2,FALSE) -> 900.113.676-9 | G29: 56218 | H29: =+G29*19% -> 10681.42 | I29: =+G29+H29 -> 66899.42 | J29: KORAZA VERDE
A30: 43304 | B30: =+TEXT(Tabla1[[#This Row],[FECHA]],"MMMM") -> julio | C30: =+TEXT(Tabla1[[#This Row],[FECHA]],"AAAA") -> lunes | D30: 2758 | E30: COMERCIALIZADORA CALYPSO S.A.S | F30: =+VLOOKUP(Tabla1[[#This Row],[PROVEEDOR]],Tabla7[],2,FALSE) -> 860.075.208-7 | G30: 9244 | H30: =+G30*19% -> 1756.36 | I30: =+G30+H30 -> 11000.36 | J30: PEGANTE MAXON
A31: 43318 | B31: =+TEXT(Tabla1[[#This Row],[FECHA]],"MMMM") -> agosto | C31: =+TEXT(Tabla1[[#This Row],[FECHA]],"AAAA") -> lunes | D31: 8716 | E31: ANDRES FERNEY PUERTA | F31: =+VLOOKUP(Tabla1[[#This Row],[PROVEEDOR]],Tabla7[],2,FALSE) -> 71.212.993-7 | G31: 51261 | H31: =+G31*19% -> 9739.59 | I31: =+G31+H31 -> 61000.59 | J31: VARIOS
A32: 43348 | B32: =+TEXT(Tabla1[[#This Row],[FECHA]],"MMMM") -> septiembre | C32: =+TEXT(Tabla1[[#This Row],[FECHA]],"AAAA") -> miércoles | D32: 490891 | E32: SODIMAC COLOMBIA | F32: =+VLOOKUP(Tabla1[[#This Row],[PROVEEDOR]],Tabla7[],2,FALSE) -> 800.242.106-2 | G32: 55378 | H32: =+G32*19% -> 10521.82 | I32: =+G32+H32 -> 65899.82 | J32: PORTAROLLO-TAPAS CABLES
A33: 43181 | B33: =+TEXT(Tabla1[[#This Row],[FECHA]],"MMMM") -> marzo | C33: =+TEXT(Tabla1[[#This Row],[FECHA]],"AAAA") -> jueves | D33: 110790 | E33: COMERCIALIZADORA CALYPSO S.A.S | F33: =+VLOOKUP(Tabla1[[#This Row],[PROVEEDOR]],Tabla7[],2,FALSE) -> 860.075.208-7 | G33: 7428.58 | H33: =+G33*19% -> 1411.4302 | I33: =+G33+H33 -> 8840.0102 | J33: VINILO CAL 400
A34: 43362 | B34: =+TEXT(Tabla1[[#This Row],[FECHA]],"MMMM") -> septiembre | C34: =+TEXT(Tabla1[[#This Row],[FECHA]],"AAAA") -> miércoles | D34: 76228 | E34: SOFIA POSADA S.A.S | F34: =+VLOOKUP(Tabla1[[#This Row],[PROVEEDOR]],Tabla7[],2,FALSE) -> 901.099.232-6 | G34: 127143 | H34: =+G34*19% -> 24157.17 | I34: =+G34+H34 -> 151300.17 | J34: YUMBOLON 15MM-PEGANTES
A35: 43367 | B35: =+TEXT(Tabla1[[#This Row],[FECHA]],"MMMM") -> septiembre | C35: =+TEXT(Tabla1[[#This Row],[FECHA]],"AAAA") -> lunes | D35: 107283 | E35: JUAN F. ESTRADA | F35: =+VLOOKUP(Tabla1[[#This Row],[PROVEEDOR]],Tabla7[],2,FALSE) -> 71.315.681-7 | G35: 29664 | H35: =+G35*19% -> 5636.16 | I35: =+G35+H35 -> 35300.16 | J35: RIATA ASCESORIOS
A36: 43364 | B36: =+TEXT(Tabla1[[#This Row],[FECHA]],"MMMM") -> septiembre | C36: =+TEXT(Tabla1[[#This Row],[FECHA]],"AAAA") -> viernes | D36: 421830 | E36: SODIMAC COLOMBIA | F36: =+VLOOKUP(Tabla1[[#This Row],[PROVEEDOR]],Tabla7[],2,FALSE) -> 800.242.106-2 | G36: 40168 | H36: =+G36*19% -> 7631.92 | I36: =+G36+H36 -> 47799.92 | J36: TORNILLOS-CERRADURA
A37: 43371 | B37: =+TEXT(Tabla1[[#This Row],[FECHA]],"MMMM") -> septiembre | C37: =+TEXT(Tabla1[[#This Row],[FECHA]],"AAAA") -> viernes | D37: 517528 | E37: SODIMAC COLOMBIA | F37: =+VLOOKUP(Tabla1[[#This Row],[PROVEEDOR]],Tabla7[],2,FALSE) -> 800.242.106-2 | G37: 183193 | H37: =+G37*19% -> 34806.67 | I37: =+G37+H37 -> 217999.67 | J37: CAMPANA-VINILTEX-LIJAS
A38: 43209 | B38: =+TEXT(Tabla1[[#This Row],[FECHA]],"MMMM") -> abril | C38: =+TEXT(Tabla1[[#This Row],[FECHA]],"AAAA") -> jueves | D38: 2038692 | E38: ALMACENES CORONA S.A.S | F38: =+VLOOKUP(Tabla1[[#This Row],[PROVEEDOR]],Tabla7[],2,FALSE) -> 860.500.480-8 | G38: 66931.09 | H38: =+G38*19% -> 12716.907 | I38: =+G38+H38 -> 79647.997 | J38: PISO SOLNA ARD CAFÉ
... A40: 43341 | B40: =+TEXT(Tabla1[[#This Row],[FECHA]],"MMMM") -> agosto | C40: =+TEXT(Tabla1[[#This Row],[FECHA]],"AAAA") -> miércoles | D40: 278062 | E40: LUZ MARINA PAMPLONA | F40: =+VLOOKUP(Tabla1[[#This Row],[PROVEEDOR]],Tabla7[],2,FALSE) -> 42.765.696-1 | G40: 75336.41 | H40: =+G40*19% -> 14313.918 | I40: =+G40+H40 -> 89650.328 | J40: VARIOS
A41: 43341 | B41: =+TEXT(Tabla1[[#This Row],[FECHA]],"MMMM") -> agosto | C41: =+TEXT(Tabla1[[#This Row],[FECHA]],"AAAA") -> miércoles | D41: 278064 | E41: LUZ MARINA PAMPLONA | F41: =+VLOOKUP(Tabla1[[#This Row],[PROVEEDOR]],Tabla7[],2,FALSE) -> 42.765.696-1 | G41: 65105.22 | H41: =+G41*19% -> 12369.992 | I41: 82075 | J41: VARIOS
A42: 43341 | B42: =+TEXT(Tabla1[[#This Row],[FECHA]],"MMMM") -> agosto | C42: =+TEXT(Tabla1[[#This Row],[FECHA]],"AAAA") -> miércoles | D42: 278065 | E42: LUZ MARINA PAMPLONA | F42: =+VLOOKUP(Tabla1[[#This Row],[PROVEEDOR]],Tabla7[],2,FALSE) -> 42.765.696-1 | G42: 101235.71 | H42: =+G42*19% -> 19234.785 | I42: =+G42+H42 -> 120470.49 | J42: VARIOS
A43: 43867 | B43: =+TEXT(Tabla1[[#This Row],[FECHA]],"MMMM") -> febrero | C43: =+TEXT(Tabla1[[#This Row],[FECHA]],"AAAA") -> jueves | D43: 185 | E43: CENTRAL DE AMORTIGUADORES | F43: =+VLOOKUP(Tabla1[[#This Row],[PROVEEDOR]],Tabla7[],2,FALSE) -> 0 | G43: 310000 | H43: 0 | I43: =+G43+H43 -> 310000 | J43: 2 AMORTIGUADORES DELANTEROS COROLLA
A44: 43881 | B44: =+TEXT(Tabla1[[#This Row],[FECHA]],"MMMM") -> febrero | C44: =+TEXT(Tabla1[[#This Row],[FECHA]],"AAAA") -> jueves | D44: 2783 | E44: PEDRO ANTONIO HERRERA | F44: =+VLOOKUP(Tabla1[[#This Row],[PROVEEDOR]],Tabla7[],2,FALSE) -> 8.228.782-0 | G44: 196394 | H44: =+G44*19% -> 37314.86 | I44: =+G44+H44 -> 233708.86 | J44: 12.3 MTS BRIGADIER 700-342
A45: 43886 | B45: =+TEXT(Tabla1[[#This Row],[FECHA]],"MMMM") -> febrero | C45: =+TEXT(Tabla1[[#This Row],[FECHA]],"AAAA") -> martes | D45: 9754 | E45: PLASTEXTIL S.A.S | F45: =+VLOOKUP(Tabla1[[#This Row],[PROVEEDOR]],Tabla7[],2,FALSE) -> 890.900.372-6 | G45: 15982 | H45: =+G45*19% -> 3036.58 | I45: =+G45+H45 -> 19018.58 | J45: 1 MTS BRIGADIER 700
A46: 43885 | B46: =+TEXT(Tabla1[[#This Row],[FECHA]],"MMMM") -> febrero | C46: =+TEXT(Tabla1[[#This Row],[FECHA]],"AAAA") -> lunes | D46: 290555 | E46: TODO TAPICERO S.A | F46: =+VLOOKUP(Tabla1[[#This Row],[PROVEEDOR]],Tabla7[],2,FALSE) -> 811.019.431-7 | G46: 20672 | H46: =+G46*19% -> 3927.68 | I46: =+G46+H46 -> 24599.68 | J46: PEGANTE-BRIGADIER
A47: 43953 | B47: =+TEXT(Tabla1[[#This Row],[FECHA]],"MMMM") -> mayo | C47: =+TEXT(Tabla1[[#This Row],[FECHA]],"AAAA") -> sábado | D47: 406768 | E47: ALMACEN PLASTITELAS S.A | F47: =+VLOOKUP(Tabla1[[#This Row],[PROVEEDOR]],Tabla7[],2,FALSE) -> 800.028.761-0 | G47: 124369 | H47: =+G47*19% -> 23630.11 | I47: =+G47+H47 -> 147999.11 | J47: VINILO CAL 30 MTS
A48: 43988 | B48: =+TEXT(Tabla1[[#This Row],[FECHA]],"MMMM") -> junio | C48: =+TEXT(Tabla1[[#This Row],[FECHA]],"AAAA") -> sábado | D48: 8008 | E48: COMERCIALIZADORA CALYPSO S.A.S | F48: =+VLOOKUP(Tabla1[[#This Row],[PROVEEDOR]],Tabla7[],2,FALSE) -> 860.075.208-7 | G48: 46387 | H48: =+G48*19% -> 8813.53 | I48: =+G48+H48 -> 55200.53 | J48: 12 MTS VINILO CAL150
A49: 43985 | B49: =+TEXT(Tabla1[[#This Row],[FECHA]],"MMMM") -> junio | C49: =+TEXT(Tabla1[[#This Row],[FECHA]],"AAAA") -> miércoles | D49: 4206 665892 | E49: SODIMAC COLOMBIA | F49: =+VLOOKUP(Tabla1[[#This Row],[PROVEEDOR]],Tabla7[],2,FALSE) -> 800.242.106-2 | G49: 121513 | H49: =+G49*19% -> 23087.47 | I49: =+G49+H49 -> 144600.47 | J49: GATO BOTELLA-CINTA DOBLE FAZ
A50: 44016 | B50: =+TEXT(Tabla1[[#This Row],[FECHA]],"MMMM") -> julio | C50: =+TEXT(Tabla1[[#This Row],[FECHA]],"AAAA") -> sábado | D50: 348028 | E50: RELOMAR S.A.S | F50: =+VLOOKUP(Tabla1[[#This Row],[PROVEEDOR]],Tabla7[],2,FALSE) -> 900.948.601-0 | G50: 42017 | H50: =+G50*19% -> 7983.23 | I50: =+G50+H50 -> 50000.23 | J50: 6 BOMBILLO $3.000--2 H3 $ 16.000
A51: 43988 | B51: =+TEXT(Tabla1[[#This Row],[FECHA]],"MMMM") -> junio | C51: =+TEXT(Tabla1[[#This Row],[FECHA]],"AAAA") -> sábado | D51: 4206 666499 | E51: SODIMAC COLOMBIA | F51: =+VLOOKUP(Tabla1[[#This Row],[PROVEEDOR]],Tabla7[],2,FALSE) -> 800.242.106-2 | G51: 78655 | H51: =+G51*19% -> 14944.45 | I51: =+G51+H51 -> 93599.45 | J51: CINTA DPBLE FAZ
A52: 44107 | B52: =+TEXT(Tabla1[[#This Row],[FECHA]],"MMMM") -> octubre | C52: =+TEXT(Tabla1[[#This Row],[FECHA]],"AAAA") -> sábado | D52: 5219861 | E52: MA. ALEJANDRA TANGARIFE | F52: =+VLOOKUP(Tabla1[[#This Row],[PROVEEDOR]],Tabla7[],2,FALSE) -> 1128422587-8 | G52: 27521 | H52: =+G52*19% -> 5228.99 | I52: =+G52+H52 -> 32749.99 | J52: RIATRA
A53: 43988 | B53: =+TEXT(Tabla1[[#This Row],[FECHA]],"MMMM") -> junio | C53: =+TEXT(Tabla1[[#This Row],[FECHA]],"AAAA") -> sábado | D53: 8886 | E53: GHMC S.A.S | F53: =+VLOOKUP(Tabla1[[#This Row],[PROVEEDOR]],Tabla7[],2,FALSE) -> 900.199.391-4 | G53: 49580 | H53: =+G53*19% -> 9420.2 | I53: =+G53+H53 -> 59000.2 | J53: CARTUCHO IMPRESORA
A54: 44048 | B54: =+TEXT(Tabla1[[#This Row],[FECHA]],"MMMM") -> agosto | C54: =+TEXT(Tabla1[[#This Row],[FECHA]],"AAAA") -> miércoles | D54: 27847 | E54: CENTRO ELECTRICO AT. E.U | F54: =+VLOOKUP(Tabla1[[#This Row],[PROVEEDOR]],Tabla7[],2,FALSE) -> 811.013.030-1 | G54: 31000 | H54: 0 | I54: =+G54+H54 -> 31000 | J54: OJO DE BUEY
A55: 44048 | B55: =+TEXT(Tabla1[[#This Row],[FECHA]],"MMMM") -> agosto | C55: =+TEXT(Tabla1[[#This Row],[FECHA]],"AAAA") -> miércoles | D55: 15985 | E55: COMERCIALIZADORA GIRALDO Z S.A.S | F55: =+VLOOKUP(Tabla1[[#This Row],[PROVEEDOR]],Tabla7[],2,FALSE) -> 900.838.480-9 | G55: 30504 | H55: =+G55*19% -> 5795.76 | I55: =+G55+H55 -> 36299.76 | J55: HILO APTAN 40
A56: 44048 | B56: =+TEXT(Tabla1[[#This Row],[FECHA]],"MMMM") -> agosto | C56: =+TEXT(Tabla1[[#This Row],[FECHA]],"AAAA") -> miércoles | D56: 98807 | E56: LUZ PIEDAD ESPINOSA | F56: =+VLOOKUP(Tabla1[[#This Row],[PROVEEDOR]],Tabla7[],2,FALSE) -> 21.395.737-0 | G56: 83361 | H56: =+G56*19% -> 15838.59 | I56: =+G56+H56 -> 99199.59 | J56: LONA BRIGADIER
A57: 44053 | B57: =+TEXT(Tabla1[[#This Row],[FECHA]],"MMMM") -> agosto | C57: =+TEXT(Tabla1[[#This Row],[FECHA]],"AAAA") -> lunes | D57: 85640 | E57: ALMACEN RAMO ELECTRICOS S.A.S | F57: =+VLOOKUP(Tabla1[[#This Row],[PROVEEDOR]],Tabla7[],2,FALSE) -> 800.175.064-4 | G57: 130252 | H57: =+G57*19% -> 24747.88 | I57: =+G57+H57 -> 154999.88 | J57: BOMBA GASOLINA COROLLA
A58: 44054 | B58: =+TEXT(Tabla1[[#This Row],[FECHA]],"MMMM") -> agosto | C58: =+TEXT(Tabla1[[#This Row],[FECHA]],"AAAA") -> martes | D58: 6833 | E58: GUILLERMO LEON BEDOYA | F58: =+VLOOKUP(Tabla1[[#This Row],[PROVEEDOR]],Tabla7[],2,FALSE) -> 71.396.968-1 | G58: 157500 | H58: 0 | I58: =+G58+H58 -> 157500 | J58: PANEL LED 18 W
A59: 44061 | B59: =+TEXT(Tabla1[[#This Row],[FECHA]],"MMMM") -> agosto | C59: =+TEXT(Tabla1[[#This Row],[FECHA]],"AAAA") -> martes | D59: 6116 | E59: FORMATEX LA 50 | F59: =+VLOOKUP(Tabla1[[#This Row],[PROVEEDOR]],Tabla7[],2,FALSE) -> 900.025.648-5 | G59: 16134 | H59: =+G59*19% -> 3065.46 | I59: =+G59+H59 -> 19199.46 | J59: HERRAJES
A60: 44055 | B60: =+TEXT(Tabla1[[#This Row],[FECHA]],"MMMM") -> agosto | C60: =+TEXT(Tabla1[[#This Row],[FECHA]],"AAAA") -> miércoles | D60: 4206 678263 | E60: SODIMAC COLOMBIA | F60: =+VLOOKUP(Tabla1[[#This Row],[PROVEEDOR]],Tabla7[],2,FALSE) -> 800.242.106-2 | G60: 36092 | H60: =+G60*19% -> 6857.48 | I60: =+G60+H60 -> 42949.48 | J60: CINTA DOBLE FAZ-BUJE PVC
A61: 44056 | B61: =+TEXT(Tabla1[[#This Row],[FECHA]],"MMMM") -> agosto | C61: =+TEXT(Tabla1[[#This Row],[FECHA]],"AAAA") -> jueves | D61: 344394 | E61: LUZ MARINA PAMPLONA | F61: =+VLOOKUP(Tabla1[[#This Row],[PROVEEDOR]],Tabla7[],2,FALSE) -> 42.765.696-1 | G61: 4705.9 | H61: =+G61*19% -> 894.121 | I61: =+G61+H61 -> 5600.021 | J61: SOLDADURA PVC
A62: 44069 | B62: =+TEXT(Tabla1[[#This Row],[FECHA]],"MMMM") -> agosto | C62: =+TEXT(Tabla1[[#This Row],[FECHA]],"AAAA") -> miércoles | D62: 1613 | E62: FIJACIONES OROZCO S.A.S | F62: =+VLOOKUP(Tabla1[[#This Row],[PROVEEDOR]],Tabla7[],2,FALSE) -> 900.378.955-6 | G62: 54800 | H62: =+G62*19% -> 10412 | I62: =+G62+H62 -> 65212 | J62: TORNILLOS -BROCAS
A63: 44069 | B63: =+TEXT(Tabla1[[#This Row],[FECHA]],"MMMM") -> agosto | C63: =+TEXT(Tabla1[[#This Row],[FECHA]],"AAAA") -> miércoles | D63: 4007 499477 | E63: SODIMAC COLOMBIA | F63: =+VLOOKUP(Tabla1[[#This Row],[PROVEEDOR]],Tabla7[],2,FALSE) -> 800.242.106-2 | G63: 14622 | H63: =+G63*19% -> 2778.18 | I63: =+G63+H63 -> 17400.18 | J63: BUJE PVC-ADAPTADOR
A64: 44107 | B64: =+TEXT(Tabla1[[#This Row],[FECHA]],"MMMM") -> octubre | C64: =+TEXT(Tabla1[[#This Row],[FECHA]],"AAAA") -> sábado | D64: 579913 | E64: ALMACEN PLASTITELAS S.A | F64: =+VLOOKUP(Tabla1[[#This Row],[PROVEEDOR]],Tabla7[],2,FALSE) -> 800.028.761-0 | G64: 200840 | H64: =+G64*19% -> 38159.6 | I64: =+G64+H64 -> 238999.6 | J64: 10 MTS ULTRA LONA AZUL
A65: 44107 | B65: =+TEXT(Tabla1[[#This Row],[FECHA]],"MMMM") -> octubre | C65: =+TEXT(Tabla1[[#This Row],[FECHA]],"AAAA") -> sábado | D65: 422134 | E65: ALMACEN PLASTITELAS S.A | F65: =+VLOOKUP(Tabla1[[#This Row],[PROVEEDOR]],Tabla7[],2,FALSE) -> 800.028.761-0 | G65: 32773 | H65: =+G65*19% -> 6226.87 | I65: =+G65+H65 -> 38999.87 | J65: 10 MTS GUATA 300
A66: 44109 | B66: =+TEXT(Tabla1[[#This Row],[FECHA]],"MMMM") -> octubre | C66: =+TEXT(Tabla1[[#This Row],[FECHA]],"AAAA") -> lunes | D66: 44553 | E66: COMERCIALIZADORA CALYPSO S.A.S | F66: =+VLOOKUP(Tabla1[[#This Row],[PROVEEDOR]],Tabla7[],2,FALSE) -> 860.075.208-7 | G66: 118487 | H66: =+G66*19% -> 22512.53 | I66: =+G66+H66 -> 140999.53 | J66: 30 MTS ARKANSAS
A67: 44136 | B67: =+TEXT(Tabla1[[#This Row],[FECHA]],"MMMM") -> noviembre | C67: =+TEXT(Tabla1[[#This Row],[FECHA]],"AAAA") -> domingo | D67: 12960 | E67: SERVITECA LUBRIFILTROS BELLO S.A.S | F67: =+VLOOKUP(Tabla1[[#This Row],[PROVEEDOR]],Tabla7[],2,FALSE) -> 900.704.790-7 | G67: 58824 | H67: =+G67*19% -> 11176.56 | I67: =+G67+H67 -> 70000.56 | J67: ACEITE 20W50--FILTRO DE ACEITE
A68: 44148 | B68: =+TEXT(Tabla1[[#This Row],[FECHA]],"MMMM") -> noviembre | C68: =+TEXT(Tabla1[[#This Row],[FECHA]],"AAAA") -> viernes | D68: 3401 | E68: COMERCIALIZADORA CALYPSO S.A.S | F68: =+VLOOKUP(Tabla1[[#This Row],[PROVEEDOR]],Tabla7[],2,FALSE) -> 860.075.208-7 | G68: 150450 | H68: =+G68*19% -> 28585.5 | I68: =+G68+H68 -> 179035.5 | J68: 6.1 MTS LONA ESPAÑA
A69: 44156 | B69: =+TEXT(Tabla1[[#This Row],[FECHA]],"MMMM") -> noviembre | C69: =+TEXT(Tabla1[[#This Row],[FECHA]],"AAAA") -> sábado | D69: 5501 | E69: COMERCIALIZADORA CALYPSO S.A.S | F69: =+VLOOKUP(Tabla1[[#This Row],[PROVEEDOR]],Tabla7[],2,FALSE) -> 860.075.208-7 | G69: 66429 | H69: =+G69*19% -> 12621.51 | I69: =+G69+H69 -> 79050.51 | J69: 13 MTS ARKANSAS
A70: 44156 | B70: =+TEXT(Tabla1[[#This Row],[FECHA]],"MMMM") -> noviembre | C70: =+TEXT(Tabla1[[#This Row],[FECHA]],"AAAA") -> sábado | D70: 429374 | E70: ALMACEN PLASTITELAS S.A | F70: =+VLOOKUP(Tabla1[[#This Row],[PROVEEDOR]],Tabla7[],2,FALSE) -> 800.028.761-0 | G70: 39328 | H70: =+G70*19% -> 7472.32 | I70: =+G70+H70 -> 46800.32 | J70: 12 MTS GUATA 300
A71: 44162 | B71: =+TEXT(Tabla1[[#This Row],[FECHA]],"MMMM") -> noviembre | C71: =+TEXT(Tabla1[[#This Row],[FECHA]],"AAAA") -> viernes | D71: 4003 | E71: PEDRO ANTONIO HERRERA | F71: =+VLOOKUP(Tabla1[[#This Row],[PROVEEDOR]],Tabla7[],2,FALSE) -> 8.228.782-0 | G71: 176470.59 | H71: =+G71*19% -> 33529.412 | I71: =+G71+H71 -> 210000 | J71: 10 MTS BRIGADIER 700
A72: 44224 | B72: =+TEXT(Tabla1[[#This Row],[FECHA]],"MMMM") -> enero | C72: =+TEXT(Tabla1[[#This Row],[FECHA]],"AAAA") -> jueves | D72: T551 163 | E72: COMERCIALIZADORA CALYPSO S.A.S | F72: =+VLOOKUP(Tabla1[[#This Row],[PROVEEDOR]],Tabla7[],2,FALSE) -> 860.075.208-7 | G72: 156092.44 | H72: =+G72*19% -> 29657.564 | I72: =+G72+H72 -> 185750 | J72: 25 MTS ARKANSAS--10 MT GUATA
A73: 44255 | B73: =+TEXT(Tabla1[[#This Row],[FECHA]],"MMMM") -> febrero | C73: =+TEXT(Tabla1[[#This Row],[FECHA]],"AAAA") -> domingo | D73: CRD-2165 | E73: CONQUILLANTAS | F73: =+VLOOKUP(Tabla1[[#This Row],[PROVEEDOR]],Tabla7[],2,FALSE) -> 71.773,073-2 | G73: 327731.09 | H73: =+G73*19% -> 62268.907 | I73: =+G73+H73 -> 390000 | J73: 2 LLANTAS BLACKLION 195/65R15--ALINEACION
H81: =+G81*19% -> 0 | I81: =+G81+H81 -> 0
H82: =+G82*19% -> 0 | I82: =+G82+H82 -> 0
H83: =+G83*19% -> 0 | I83: =+G83+H83 -> 0
H84: =+G84*19% -> 0 | I84: =+G84+H84 -> 0
H85: =+G85*19% -> 0 | I85: =+G85+H85 -> 0
H86: =+G86*19% -> 0 | I86: =+G86+H86 -> 0
H87: =+G87*19% -> 0 | I87: =+G87+H87 -> 0
H88: =+G88*19% -> 0 | I88: =+G88+H88 -> 0

Sheet RESUMEN COMPRAS
A2: CONSOLIDADO X AÑOS
A3: COMPRAS
B4: TOTALES | C4: =+SUM(Tabla8[2018]) -> 0 | D4: =+SUM(Tabla8[2019]) -> 0 | E4: =+SUM(Tabla8[2020]) -> 0 | F4: =+SUM(Tabla8[2021]) -> 0
A5: PROV/AÑO | B5: ACUMULADO | C5: 2018 | D5: 2019 | E5: 2020 | F5: 2021
A6: =B.D!F42 -> CONQUILLANTAS | B6: =+SUM(Tabla8[[#This Row],[2018]:[2021]]) -> 0 | C6: =+SUMIFS(COMPRAS!$I$4:$I$80,COMPRAS!$E$4:$E$80,Tabla8[[#This Row],[PROV/AÑO]],COMPRAS!$C$4:$C$80,Tabla8[[#Headers],[2018]]) -> 0 | D6: =+SUMIFS(COMPRAS!I42:I118,COMPRAS!E42:E118,Tabla8[[#This Row],[PROV/AÑO]],COMPRAS!C42:C118,Tabla8[[#Headers],[2019]]) -> 0 | E6: =+SUMIFS(COMPRAS!$I$4:$I$80,COMPRAS!$E$4:$E$80,Tabla8[[#This Row],[PROV/AÑO]],COMPRAS!$C$4:$C$80,Tabla8[[#Headers],[2020]]) -> 0 | F6: =+SUMIFS(COMPRAS!$I$4:$I$80,COMPRAS!$E$4:$E$80,Tabla8[[#This Row],[PROV/AÑO]],COMPRAS!$C$4:$C$80,Tabla8[[#Headers],[2021]]) -> 0
A7: =B.D!F43 -> 0 | B7: =+SUM(Tabla8[[#This Row],[2018]:[2021]]) -> 0 | C7: =+SUMIFS(COMPRAS!$I$4:$I$80,COMPRAS!$E$4:$E$80,Tabla8[[#This Row],[PROV/AÑO]],COMPRAS!$C$4:$C$80,Tabla8[[#Headers],[2018]]) -> 0 | D7: =+SUMIFS(COMPRAS!I43:I119,COMPRAS!E43:E119,Tabla8[[#This Row],[PROV/AÑO]],COMPRAS!C43:C119,Tabla8[[#Headers],[2019]]) -> 0 | E7: =+SUMIFS(COMPRAS!$I$4:$I$80,COMPRAS!$E$4:$E$80,Tabla8[[#This Row],[PROV/AÑO]],COMPRAS!$C$4:$C$80,Tabla8[[#Headers],[2020]]) -> 0 | F7: =+SUMIFS(COMPRAS!$I$4:$I$80,COMPRAS!$E$4:$E$80,Tabla8[[#This Row],[PROV/AÑO]],COMPRAS!$C$4:$C$80,Tabla8[[#Headers],[2021]]) -> 0
A8: =B.D!F44 -> 0 | B8: =+SUM(Tabla8[[#This Row],[2018]:[2021]]) -> 0 | C8: =+SUMIFS(COMPRAS!$I$4:$I$80,COMPRAS!$E$4:$E$80,Tabla8[[#This Row],[PROV/AÑO]],COMPRAS!$C$4:$C$80,Tabla8[[#Headers],[2018]]) -> 0 | D8: =+SUMIFS(COMPRAS!I44:I120,COMPRAS!E44:E120,Tabla8[[#This Row],[PROV/AÑO]],COMPRAS!C44:C120,Tabla8[[#Headers],[2019]]) -> 0 | E8: =+SUMIFS(COMPRAS!$I$4:$I$80,COMPRAS!$E$4:$E$80,Tabla8[[#This Row],[PROV/AÑO]],COMPRAS!$C$4:$C$80,Tabla8[[#Headers],[2020]]) -> 0 | F8: =+SUMIFS(COMPRAS!$I$4:$I$80,COMPRAS!$E$4:$E$80,Tabla8[[#This Row],[PROV/AÑO]],COMPRAS!$C$4:$C$80,Tabla8[[#Headers],[2021]]) -> 0
A9: =B.D!F30 -> ALMACEN PLASTITELAS S.A | B9: =+SUM(Tabla8[[#This Row],[2018]:[2021]]) -> 0 | C9: =+SUMIFS(COMPRAS!$I$4:$I$80,COMPRAS!$E$4:$E$80,Tabla8[[#This Row],[PROV/AÑO]],COMPRAS!$C$4:$C$80,Tabla8[[#Headers],[2018]]) -> 0 | D9: =+SUMIFS(COMPRAS!I30:I106,COMPRAS!E30:E106,Tabla8[[#This Row],[PROV/AÑO]],COMPRAS!C30:C106,Tabla8[[#Headers],[2019]]) -> 0 | E9: =+SUMIFS(COMPRAS!$I$4:$I$80,COMPRAS!$E$4:$E$80,Tabla8[[#This Row],[PROV/AÑO]],COMPRAS!$C$4:$C$80,Tabla8[[#Headers],[2020]]) -> 0 | F9: =+SUMIFS(COMPRAS!$I$4:$I$80,COMPRAS!$E$4:$E$80,Tabla8[[#This Row],[PROV/AÑO]],COMPRAS!$C$4:$C$80,Tabla8[[#Headers],[2021]]) -> 0
A10: =B.D!F37 -> ALMACEN RAMO ELECTRICOS S.A.S | B10: =+SUM(Tabla8[[#This Row],[2018]:[2021]]) -> 0 | C10: =+SUMIFS(COMPRAS!$I$4:$I$80,COMPRAS!$E$4:$E$80,Tabla8[[#This Row],[PROV/AÑO]],COMPRAS!$C$4:$C$80,Tabla8[[#Headers],[2018]]) -> 0 | D10: =+SUMIFS(COMPRAS!I37:I113,COMPRAS!E37:E113,Tabla8[[#This Row],[PROV/AÑO]],COMPRAS!C37:C113,Tabla8[[#Headers],[2019]]) -> 0 | E10: =+SUMIFS(COMPRAS!$I$4:$I$80,COMPRAS!$E$4:$E$80,Tabla8[[#This Row],[PROV/AÑO]],COMPRAS!$C$4:$C$80,Tabla8[[#Headers],[2020]]) -> 0 | F10: =+SUMIFS(COMPRAS!$I$4:$I$80,COMPRAS!$E$4:$E$80,Tabla8[[#This Row],[PROV/AÑO]],COMPRAS!$C$4:$C$80,Tabla8[[#Headers],[2021]]) -> 0
A11: =B.D!F18 -> ALMACENES CORONA S.A.S | B11: =+SUM(Tabla8[[#This Row],[2018]:[2021]]) -> 0 | C11: =+SUMIFS(COMPRAS!$I$4:$I$80,COMPRAS!$E$4:$E$80,Tabla8[[#This Row],[PROV/AÑO]],COMPRAS!$C$4:$C$80,Tabla8[[#Headers],[2018]]) -> 0 | D11: =+SUMIFS(COMPRAS!I18:I57,COMPRAS!E18:E57,Tabla8[[#This Row],[PROV/AÑO]],COMPRAS!C18:C57,Tabla8[[#Headers],[2019]]) -> 0 | E11: =+SUMIFS(COMPRAS!$I$4:$I$80,COMPRAS!$E$4:$E$80,Tabla8[[#This Row],[PROV/AÑO]],COMPRAS!$C$4:$C$80,Tabla8[[#Headers],[2020]]) -> 0 | F11: =+SUMIFS(COMPRAS!$I$4:$I$80,COMPRAS!$E$4:$E$80,Tabla8[[#This Row],[PROV/AÑO]],COMPRAS!$C$4:$C$80,Tabla8[[#Headers],[2021]]) -> 0
A12: =B.D!F13 -> ANDRES FERNEY PUERTA | B12: =+SUM(Tabla8[[#This Row],[2018]:[2021]]) -> 0 | C12: =+SUMIFS(COMPRAS!$I$4:$I$80,COMPRAS!$E$4:$E$80,Tabla8[[#This Row],[PROV/AÑO]],COMPRAS!$C$4:$C$80,Tabla8[[#Headers],[2018]]) -> 0 | D12: =+SUMIFS(COMPRAS!I13:I52,COMPRAS!E13:E52,Tabla8[[#This Row],[PROV/AÑO]],COMPRAS!C13:C52,Tabla8[[#Headers],[2019]]) -> 0 | E12: =+SUMIFS(COMPRAS!$I$4:$I$80,COMPRAS!$E$4:$E$80,Tabla8[[#This Row],[PROV/AÑO]],COMPRAS!$C$4:$C$80,Tabla8[[#Headers],[2020]]) -> 0 | F12: =+SUMIFS(COMPRAS!$I$4:$I$80,COMPRAS!$E$4:$E$80,Tabla8[[#This Row],[PROV/AÑO]],COMPRAS!$C$4:$C$80,Tabla8[[#Headers],[2021]]) -> 0
A13: =B.D!F23 -> ANDRES FERNEY PUERTA | B13: =+SUM(Tabla8[[#This Row],[2018]:[2021]]) -> 0 | C13: =+SUMIFS(COMPRAS!$I$4:$I$80,COMPRAS!$E$4:$E$80,Tabla8[[#This Row],[PROV/AÑO]],COMPRAS!$C$4:$C$80,Tabla8[[#Headers],[2018]]) -> 0 | D13: =+SUMIFS(COMPRAS!I23:I62,COMPRAS!E23:E62,Tabla8[[#This Row],[PROV/AÑO]],COMPRAS!C23:C62,Tabla8[[#Headers],[2019]]) -> 0 | E13: =+SUMIFS(COMPRAS!$I$4:$I$80,COMPRAS!$E$4:$E$80,Tabla8[[#This Row],[PROV/AÑO]],COMPRAS!$C$4:$C$80,Tabla8[[#Headers],[2020]]) -> 0 | F13: =+SUMIFS(COMPRAS!$I$4:$I$80,COMPRAS!$E$4:$E$80,Tabla8[[#This Row],[PROV/AÑO]],COMPRAS!$C$4:$C$80,Tabla8[[#Headers],[2021]]) -> 0
A14: =B.D!F11 -> AREA TUNNING LUJOS Y SONIDOS S.A.S | B14: =+SUM(Tabla8[[#This Row],[2018]:[2021]]) -> 0 | C14: =+SUMIFS(COMPRAS!$I$4:$I$80,COMPRAS!$E$4:$E$80,Tabla8[[#This Row],[PROV/AÑO]],COMPRAS!$C$4:$C$80,Tabla8[[#Headers],[2018]]) -> 0 | D14: =+SUMIFS(COMPRAS!I11:I50,COMPRAS!E11:E50,Tabla8[[#This Row],[PROV/AÑO]],COMPRAS!C11:C50,Tabla8[[#Headers],[2019]]) -> 0 | E14: =+SUMIFS(COMPRAS!$I$4:$I$80,COMPRAS!$E$4:$E$80,Tabla8[[#This Row],[PROV/AÑO]],COMPRAS!$C$4:$C$80,Tabla8[[#Headers],[2020]]) -> 0 | F14: =+SUMIFS(COMPRAS!$I$4:$I$80,COMPRAS!$E$4:$E$80,Tabla8[[#This Row],[PROV/AÑO]],COMPRAS!$C$4:$C$80,Tabla8[[#Headers],[2021]]) -> 0
A15: =B.D!F20 -> AUTOLATAS S.A.S | B15: =+SUM(Tabla8[[#This Row],[2018]:[2021]]) -> 0 | C15: =+SUMIFS(COMPRAS!$I$4:$I$80,COMPRAS!$E$4:$E$80,Tabla8[[#This Row],[PROV/AÑO]],COMPRAS!$C$4:$C$80,Tabla8[[#Headers],[2018]]) -> 0 | D15: =+SUMIFS(COMPRAS!I20:I59,COMPRAS!E20:E59,Tabla8[[#This Row],[PROV/AÑO]],COMPRAS!C20:C59,Tabla8[[#Headers],[2019]]) -> 0 | E15: =+SUMIFS(COMPRAS!$I$4:$I$80,COMPRAS!$E$4:$E$80,Tabla8[[#This Row],[PROV/AÑO]],COMPRAS!$C$4:$C$80,Tabla8[[#Headers],[2020]]) -> 0 | F15: =+SUMIFS(COMPRAS!$I$4:$I$80,COMPRAS!$E$4:$E$80,Tabla8[[#This Row],[PROV/AÑO]],COMPRAS!$C$4:$C$80,Tabla8[[#Headers],[2021]]) -> 0
A16: =B.D!F8 -> CENCOSUD COLOMBIA S.A | B16: =+SUM(Tabla8[[#This Row],[2018]:[2021]]) -> 0 | C16: =+SUMIFS(COMPRAS!$I$4:$I$80,COMPRAS!$E$4:$E$80,Tabla8[[#This Row],[PROV/AÑO]],COMPRAS!$C$4:$C$80,Tabla8[[#Headers],[2018]]) -> 0 | D16: =+SUMIFS(COMPRAS!I8:I47,COMPRAS!E8:E47,Tabla8[[#This Row],[PROV/AÑO]],COMPRAS!C8:C47,Tabla8[[#Headers],[2019]]) -> 0 | E16: =+SUMIFS(COMPRAS!$I$4:$I$80,COMPRAS!$E$4:$E$80,Tabla8[[#This Row],[PROV/AÑO]],COMPRAS!$C$4:$C$80,Tabla8[[#Headers],[2020]]) -> 0 | F16: =+SUMIFS(COMPRAS!$I$4:$I$80,COMPRAS!$E$4:$E$80,Tabla8[[#This Row],[PROV/AÑO]],COMPRAS!$C$4:$C$80,Tabla8[[#Headers],[2021]]) -> 0
A17: =B.D!F26 -> CENTRAL DE AMORTIGUADORES | B17: =+SUM(Tabla8[[#This Row],[2018]:[2021]]) -> 0 | C17: =+SUMIFS(COMPRAS!$I$4:$I$80,COMPRAS!$E$4:$E$80,Tabla8[[#This Row],[PROV/AÑO]],COMPRAS!$C$4:$C$80,Tabla8[[#Headers],[2018]]) -> 0 | D17: =+SUMIFS(COMPRAS!I26:I65,COMPRAS!E26:E65,Tabla8[[#This Row],[PROV/AÑO]],COMPRAS!C26:C65,Tabla8[[#Headers],[2019]]) -> 0 | E17: =+SUMIFS(COMPRAS!$I$4:$I$80,COMPRAS!$E$4:$E$80,Tabla8[[#This Row],[PROV/AÑO]],COMPRAS!$C$4:$C$80,Tabla8[[#Headers],[2020]]) -> 0 | F17: =+SUMIFS(COMPRAS!$I$4:$I$80,COMPRAS!$E$4:$E$80,Tabla8[[#This Row],[PROV/AÑO]],COMPRAS!$C$4:$C$80,Tabla8[[#Headers],[2021]]) -> 0
A18: =B.D!F12 -> CENTRO DE SERVICIOS BELLO S.A.S. | B18: =+SUM(Tabla8[[#This Row],[2018]:[2021]]) -> 0 | C18: =+SUMIFS(COMPRAS!$I$4:$I$80,COMPRAS!$E$4:$E$80,Tabla8[[#This Row],[PROV/AÑO]],COMPRAS!$C$4:$C$80,Tabla8[[#Headers],[2018]]) -> 0 | D18: =+SUMIFS(COMPRAS!I12:I51,COMPRAS!E12:E51,Tabla8[[#This Row],[PROV/AÑO]],COMPRAS!C12:C51,Tabla8[[#Headers],[2019]]) -> 0 | E18: =+SUMIFS(COMPRAS!$I$4:$I$80,COMPRAS!$E$4:$E$80,Tabla8[[#This Row],[PROV/AÑO]],COMPRAS!$C$4:$C$80,Tabla8[[#Headers],[2020]]) -> 0 | F18: =+SUMIFS(COMPRAS!$I$4:$I$80,COMPRAS!$E$4:$E$80,Tabla8[[#This Row],[PROV/AÑO]],COMPRAS!$C$4:$C$80,Tabla8[[#Headers],[2021]]) -> 0
A19: =B.D!F34 -> CENTRO ELECTRICO AT. E.U | B19: =+SUM(Tabla8[[#This Row],[2018]:[2021]]) -> 0 | C19: =+SUMIFS(COMPRAS!$I$4:$I$80,COMPRAS!$E$4:$E$80,Tabla8[[#This Row],[PROV/AÑO]],COMPRAS!$C$4:$C$80,Tabla8[[#Headers],[2018]]) -> 0 | D19: =+SUMIFS(COMPRAS!I34:I110,COMPRAS!E34:E110,Tabla8[[#This Row],[PROV/AÑO]],COMPRAS!C34:C110,Tabla8[[#Headers],[2019]]) -> 0 | E19: =+SUMIFS(COMPRAS!$I$4:$I$80,COMPRAS!$E$4:$E$80,Tabla8[[#This Row],[PROV/AÑO]],COMPRAS!$C$4:$C$80,Tabla8[[#Headers],[2020]]) -> 0 | F19: =+SUMIFS(COMPRAS!$I$4:$I$80,COMPRAS!$E$4:$E$80,Tabla8[[#This Row],[PROV/AÑO]],COMPRAS!$C$4:$C$80,Tabla8[[#Headers],[2021]]) -> 0
A20: =B.D!F25 -> COEXITO S.A.S | B20: =+SUM(Tabla8[[#This Row],[2018]:[2021]]) -> 0 | C20: =+SUMIFS(COMPRAS!$I$4:$I$80,COMPRAS!$E$4:$E$80,Tabla8[[#This Row],[PROV/AÑO]],COMPRAS!$C$4:$C$80,Tabla8[[#Headers],[2018]]) -> 0 | D20: =+SUMIFS(COMPRAS!I25:I64,COMPRAS!E25:E64,Tabla8[[#This Row],[PROV/AÑO]],COMPRAS!C25:C64,Tabla8[[#Headers],[2019]]) -> 0 | E20: =+SUMIFS(COMPRAS!$I$4:$I$80,COMPRAS!$E$4:$E$80,Tabla8[[#This Row],[PROV/AÑO]],COMPRAS!$C$4:$C$80,Tabla8[[#Headers],[2020]]) -> 0 | F20: =+SUMIFS(COMPRAS!$I$4:$I$80,COMPRAS!$E$4:$E$80,Tabla8[[#This Row],[PROV/AÑO]],COMPRAS!$C$4:$C$80,Tabla8[[#Headers],[2021]]) -> 0
A21: =B.D!F9 -> COMERCIALIZADORA CALYPSO S.A.S | B21: =+SUM(Tabla8[[#This Row],[2018]:[2021]]) -> 0 | C21: =+SUMIFS(COMPRAS!$I$4:$I$80,COMPRAS!$E$4:$E$80,Tabla8[[#This Row],[PROV/AÑO]],COMPRAS!$C$4:$C$80,Tabla8[[#Headers],[2018]]) -> 0 | D21: =+SUMIFS(COMPRAS!I9:I48,COMPRAS!E9:E48,Tabla8[[#This Row],[PROV/AÑO]],COMPRAS!C9:C48,Tabla8[[#Headers],[2019]]) -> 0 | E21: =+SUMIFS(COMPRAS!$I$4:$I$80,COMPRAS!$E$4:$E$80,Tabla8[[#This Row],[PROV/AÑO]],COMPRAS!$C$4:$C$80,Tabla8[[#Headers],[2020]]) -> 0 | F21: =+SUMIFS(COMPRAS!$I$4:$I$80,COMPRAS!$E$4:$E$80,Tabla8[[#This Row],[PROV/AÑO]],COMPRAS!$C$4:$C$80,Tabla8[[#Headers],[2021]]) -> 0
A22: =B.D!F35 -> COMERCIALIZADORA GIRALDO Z S.A.S | B22: =+SUM(Tabla8[[#This Row],[2018]:[2021]]) -> 0 | C22: =+SUMIFS(COMPRAS!$I$4:$I$80,COMPRAS!$E$4:$E$80,Tabla8[[#This Row],[PROV/AÑO]],COMPRAS!$C$4:$C$80,Tabla8[[#Headers],[2018]]) -> 0 | D22: =+SUMIFS(COMPRAS!I35:I111,COMPRAS!E35:E111,Tabla8[[#This Row],[PROV/AÑO]],COMPRAS!C35:C111,Tabla8[[#Headers],[2019]]) -> 0 | E22: =+SUMIFS(COMPRAS!$I$4:$I$80,COMPRAS!$E$4:$E$80,Tabla8[[#This Row],[PROV/AÑO]],COMPRAS!$C$4:$C$80,Tabla8[[#Headers],[2020]]) -> 0 | F22: =+SUMIFS(COMPRAS!$I$4:$I$80,COMPRAS!$E$4:$E$80,Tabla8[[#This Row],[PROV/AÑO]],COMPRAS!$C$4:$C$80,Tabla8[[#Headers],[2021]]) -> 0
A23: =B.D!F6 -> ESPINTURAS S.A.S | B23: =+SUM(Tabla8[[#This Row],[2018]:[2021]]) -> 0 | C23: =+SUMIFS(COMPRAS!$I$4:$I$80,COMPRAS!$E$4:$E$80,Tabla8[[#This Row],[PROV/AÑO]],COMPRAS!$C$4:$C$80,Tabla8[[#Headers],[2018]]) -> 0 | D23: =+SUMIFS(COMPRAS!I6:I45,COMPRAS!E6:E45,Tabla8[[#This Row],[PROV/AÑO]],COMPRAS!C6:C45,Tabla8[[#Headers],[2019]]) -> 0 | E23: =+SUMIFS(COMPRAS!$I$4:$I$80,COMPRAS!$E$4:$E$80,Tabla8[[#This Row],[PROV/AÑO]],COMPRAS!$C$4:$C$80,Tabla8[[#Headers],[2020]]) -> 0 | F23: =+SUMIFS(COMPRAS!$I$4:$I$80,COMPRAS!$E$4:$E$80,Tabla8[[#This Row],[PROV/AÑO]],COMPRAS!$C$4:$C$80,Tabla8[[#Headers],[2021]]) -> 0
A24: =B.D!F14 -> FERROSVEL S.A.S | B24: =+SUM(Tabla8[[#This Row],[2018]:[2021]]) -> 0 | C24: =+SUMIFS(COMPRAS!$I$4:$I$80,COMPRAS!$E$4:$E$80,Tabla8[[#This Row],[PROV/AÑO]],COMPRAS!$C$4:$C$80,Tabla8[[#Headers],[2018]]) -> 0 | D24: =+SUMIFS(COMPRAS!I14:I53,COMPRAS!E14:E53,Tabla8[[#This Row],[PROV/AÑO]],COMPRAS!C14:C53,Tabla8[[#Headers],[2019]]) -> 0 | E24: =+SUMIFS(COMPRAS!$I$4:$I$80,COMPRAS!$E$4:$E$80,Tabla8[[#This Row],[PROV/AÑO]],COMPRAS!$C$4:$C$80,Tabla8[[#Headers],[2020]]) -> 0 | F24: =+SUMIFS(COMPRAS!$I$4:$I$80,COMPRAS!$E$4:$E$80,Tabla8[[#This Row],[PROV/AÑO]],COMPRAS!$C$4:$C$80,Tabla8[[#Headers],[2021]]) -> 0
A25: =B.D!F40 -> FIJACIONES OROZCO S.A.S | B25: =+SUM(Tabla8[[#This Row],[2018]:[2021]]) -> 0 | C25: =+SUMIFS(COMPRAS!$I$4:$I$80,COMPRAS!$E$4:$E$80,Tabla8[[#This Row],[PROV/AÑO]],COMPRAS!$C$4:$C$80,Tabla8[[#Headers],[2018]]) -> 0 | D25: =+SUMIFS(COMPRAS!I40:I116,COMPRAS!E40:E116,Tabla8[[#This Row],[PROV/AÑO]],COMPRAS!C40:C116,Tabla8[[#Headers],[2019]]) -> 0 | E25: =+SUMIFS(COMPRAS!$I$4:$I$80,COMPRAS!$E$4:$E$80,Tabla8[[#This Row],[PROV/AÑO]],COMPRAS!$C$4:$C$80,Tabla8[[#Headers],[2020]]) -> 0 | F25: =+SUMIFS(COMPRAS!$I$4:$I$80,COMPRAS!$E$4:$E$80,Tabla8[[#This Row],[PROV/AÑO]],COMPRAS!$C$4:$C$80,Tabla8[[#Headers],[2021]]) -> 0
A26: =B.D!F39 -> FORMATEX LA 50 | B26: =+SUM(Tabla8[[#This Row],[2018]:[2021]]) -> 0 | C26: =+SUMIFS(COMPRAS!$I$4:$I$80,COMPRAS!$E$4:$E$80,Tabla8[[#This Row],[PROV/AÑO]],COMPRAS!$C$4:$C$80,Tabla8[[#Headers],[2018]]) -> 0 | D26: =+SUMIFS(COMPRAS!I39:I115,COMPRAS!E39:E115,Tabla8[[#This Row],[PROV/AÑO]],COMPRAS!C39:C115,Tabla8[[#Headers],[2019]]) -> 0 | E26: =+SUMIFS(COMPRAS!$I$4:$I$80,COMPRAS!$E$4:$E$80,Tabla8[[#This Row],[PROV/AÑO]],COMPRAS!$C$4:$C$80,Tabla8[[#Headers],[2020]]) -> 0 | F26: =+SUMIFS(COMPRAS!$I$4:$I$80,COMPRAS!$E$4:$E$80,Tabla8[[#This Row],[PROV/AÑO]],COMPRAS!$C$4:$C$80,Tabla8[[#Headers],[2021]]) -> 0
A27: =B.D!F33 -> GHMC S.A.S | B27: =+SUM(Tabla8[[#This Row],[2018]:[2021]]) -> 0 | C27: =+SUMIFS(COMPRAS!$I$4:$I$80,COMPRAS!$E$4:$E$80,Tabla8[[#This Row],[PROV/AÑO]],COMPRAS!$C$4:$C$80,Tabla8[[#Headers],[2018]]) -> 0 | D27: =+SUMIFS(COMPRAS!I33:I109,COMPRAS!E33:E109,Tabla8[[#This Row],[PROV/AÑO]],COMPRAS!C33:C109,Tabla8[[#Headers],[2019]]) -> 0 | E27: =+SUMIFS(COMPRAS!$I$4:$I$80,COMPRAS!$E$4:$E$80,Tabla8[[#This Row],[PROV/AÑO]],COMPRAS!$C$4:$C$80,Tabla8[[#Headers],[2020]]) -> 0 | F27: =+SUMIFS(COMPRAS!$I$4:$I$80,COMPRAS!$E$4:$E$80,Tabla8[[#This Row],[PROV/AÑO]],COMPRAS!$C$4:$C$80,Tabla8[[#Headers],[2021]]) -> 0
A28: =B.D!F38 -> GUILLERMO LEON BEDOYA | B28: =+SUM(Tabla8[[#This Row],[2018]:[2021]]) -> 0 | C28: =+SUMIFS(COMPRAS!$I$4:$I$80,COMPRAS!$E$4:$E$80,Tabla8[[#This Row],[PROV/AÑO]],COMPRAS!$C$4:$C$80,Tabla8[[#Headers],[2018]]) -> 0 | D28: =+SUMIFS(COMPRAS!I38:I114,COMPRAS!E38:E114,Tabla8[[#This Row],[PROV/AÑO]],COMPRAS!C38:C114,Tabla8[[#Headers],[2019]]) -> 0 | E28: =+SUMIFS(COMPRAS!$I$4:$I$80,COMPRAS!$E$4:$E$80,Tabla8[[#This Row],[PROV/AÑO]],COMPRAS!$C$4:$C$80,Tabla8[[#Headers],[2020]]) -> 0 | F28: =+SUMIFS(COMPRAS!$I$4:$I$80,COMPRAS!$E$4:$E$80,Tabla8[[#This Row],[PROV/AÑO]],COMPRAS!$C$4:$C$80,Tabla8[[#Headers],[2021]]) -> 0
A29: =B.D!F4 -> INDUSTRIAS JB S.A.S | B29: =+SUM(Tabla8[[#This Row],[2018]:[2021]]) -> 0 | C29: =+SUMIFS(COMPRAS!$I$4:$I$80,COMPRAS!$E$4:$E$80,Tabla8[[#This Row],[PROV/AÑO]],COMPRAS!$C$4:$C$80,Tabla8[[#Headers],[2018]]) -> 0 | D29: =+SUMIFS(COMPRAS!I4:I43,COMPRAS!E4:E43,Tabla8[[#This Row],[PROV/AÑO]],COMPRAS!C4:C43,Tabla8[[#Headers],[2019]]) -> 0 | E29: =+SUMIFS(COMPRAS!$I$4:$I$80,COMPRAS!$E$4:$E$80,Tabla8[[#This Row],[PROV/AÑO]],COMPRAS!$C$4:$C$80,Tabla8[[#Headers],[2020]]) -> 0 | F29: =+SUMIFS(COMPRAS!$I$4:$I$80,COMPRAS!$E$4:$E$80,Tabla8[[#This Row],[PROV/AÑO]],COMPRAS!$C$4:$C$80,Tabla8[[#Headers],[2021]]) -> 0
A30: =B.D!F22 -> J&J ASOCIADOS | B30: =+SUM(Tabla8[[#This Row],[2018]:[2021]]) -> 0 | C30: =+SUMIFS(COMPRAS!$I$4:$I$80,COMPRAS!$E$4:$E$80,Tabla8[[#This Row],[PROV/AÑO]],COMPRAS!$C$4:$C$80,Tabla8[[#Headers],[2018]]) -> 0 | D30: =+SUMIFS(COMPRAS!I22:I61,COMPRAS!E22:E61,Tabla8[[#This Row],[PROV/AÑO]],COMPRAS!C22:C61,Tabla8[[#Headers],[2019]]) -> 0 | E30: =+SUMIFS(COMPRAS!$I$4:$I$80,COMPRAS!$E$4:$E$80,Tabla8[[#This Row],[PROV/AÑO]],COMPRAS!$C$4:$C$80,Tabla8[[#Headers],[2020]]) -> 0 | F30: =+SUMIFS(COMPRAS!$I$4:$I$80,COMPRAS!$E$4:$E$80,Tabla8[[#This Row],[PROV/AÑO]],COMPRAS!$C$4:$C$80,Tabla8[[#Headers],[2021]]) -> 0
A31: =B.D!F17 -> JUAN F. ESTRADA | B31: =+SUM(Tabla8[[#This Row],[2018]:[2021]]) -> 0 | C31: =+SUMIFS(COMPRAS!$I$4:$I$80,COMPRAS!$E$4:$E$80,Tabla8[[#This Row],[PROV/AÑO]],COMPRAS!$C$4:$C$80,Tabla8[[#Headers],[2018]]) -> 0 | D31: =+SUMIFS(COMPRAS!I17:I56,COMPRAS!E17:E56,Tabla8[[#This Row],[PROV/AÑO]],COMPRAS!C17:C56,Tabla8[[#Headers],[2019]]) -> 0 | E31: =+SUMIFS(COMPRAS!$I$4:$I$80,COMPRAS!$E$4:$E$80,Tabla8[[#This Row],[PROV/AÑO]],COMPRAS!$C$4:$C$80,Tabla8[[#Headers],[2020]]) -> 0 | F31: =+SUMIFS(COMPRAS!$I$4:$I$80,COMPRAS!$E$4:$E$80,Tabla8[[#This Row],[PROV/AÑO]],COMPRAS!$C$4:$C$80,Tabla8[[#Headers],[2021]]) -> 0
A32: =B.D!F5 -> LUZ MARINA PAMPLONA | B32: =+SUM(Tabla8[[#This Row],[2018]:[2021]]) -> 0 | C32: =+SUMIFS(COMPRAS!$I$4:$I$80,COMPRAS!$E$4:$E$80,Tabla8[[#This Row],[PROV/AÑO]],COMPRAS!$C$4:$C$80,Tabla8[[#Headers],[2018]]) -> 0 | D32: =+SUMIFS(COMPRAS!I5:I44,COMPRAS!E5:E44,Tabla8[[#This Row],[PROV/AÑO]],COMPRAS!C5:C44,Tabla8[[#Headers],[2019]]) -> 0 | E32: =+SUMIFS(COMPRAS!$I$4:$I$80,COMPRAS!$E$4:$E$80,Tabla8[[#This Row],[PROV/AÑO]],COMPRAS!$C$4:$C$80,Tabla8[[#Headers],[2020]]) -> 0 | F32: =+SUMIFS(COMPRAS!$I$4:$I$80,COMPRAS!$E$4:$E$80,Tabla8[[#This Row],[PROV/AÑO]],COMPRAS!$C$4:$C$80,Tabla8[[#Headers],[2021]]) -> 0
A33: =B.D!F36 -> LUZ PIEDAD ESPINOSA | B33: =+SUM(Tabla8[[#This Row],[2018]:[2021]]) -> 0 | C33: =+SUMIFS(COMPRAS!$I$4:$I$80,COMPRAS!$E$4:$E$80,Tabla8[[#This Row],[PROV/AÑO]],COMPRAS!$C$4:$C$80,Tabla8[[#Headers],[2018]]) -> 0 | D33: =+SUMIFS(COMPRAS!I36:I112,COMPRAS!E36:E112,Tabla8[[#This Row],[PROV/AÑO]],COMPRAS!C36:C112,Tabla8[[#Headers],[2019]]) -> 0 | E33: =+SUMIFS(COMPRAS!$I$4:$I$80,COMPRAS!$E$4:$E$80,Tabla8[[#This Row],[PROV/AÑO]],COMPRAS!$C$4:$C$80,Tabla8[[#Headers],[2020]]) -> 0 | F33: =+SUMIFS(COMPRAS!$I$4:$I$80,COMPRAS!$E$4:$E$80,Tabla8[[#This Row],[PROV/AÑO]],COMPRAS!$C$4:$C$80,Tabla8[[#Headers],[2021]]) -> 0
A34: =B.D!F32 -> MA. ALEJANDRA TANGARIFE | B34: =+SUM(Tabla8[[#This Row],[2018]:[2021]]) -> 0 | C34: =+SUMIFS(COMPRAS!$I$4:$I$80,COMPRAS!$E$4:$E$80,Tabla8[[#This Row],[PROV/AÑO]],COMPRAS!$C$4:$C$80,Tabla8[[#Headers],[2018]]) -> 0 | D34: =+SUMIFS(COMPRAS!I32:I108,COMPRAS!E32:E108,Tabla8[[#This Row],[PROV/AÑO]],COMPRAS!C32:C108,Tabla8[[#Headers],[2019]]) -> 0 | E34: =+SUMIFS(COMPRAS!$I$4:$I$80,COMPRAS!$E$4:$E$80,Tabla8[[#This Row],[PROV/AÑO]],COMPRAS!$C$4:$C$80,Tabla8[[#Headers],[2020]]) -> 0 | F34: =+SUMIFS(COMPRAS!$I$4:$I$80,COMPRAS!$E$4:$E$80,Tabla8[[#This Row],[PROV/AÑO]],COMPRAS!$C$4:$C$80,Tabla8[[#Headers],[2021]]) -> 0
A35: =B.D!F21 -> MATERIALES EL TITAN 1 S.A.S | B35: =+SUM(Tabla8[[#This Row],[2018]:[2021]]) -> 0 | C35: =+SUMIFS(COMPRAS!$I$4:$I$80,COMPRAS!$E$4:$E$80,Tabla8[[#This Row],[PROV/AÑO]],COMPRAS!$C$4:$C$80,Tabla8[[#Headers],[2018]]) -> 0 | D35: =+SUMIFS(COMPRAS!I21:I60,COMPRAS!E21:E60,Tabla8[[#This Row],[PROV/AÑO]],COMPRAS!C21:C60,Tabla8[[#Headers],[2019]]) -> 0 | E35: =+SUMIFS(COMPRAS!$I$4:$I$80,COMPRAS!$E$4:$E$80,Tabla8[[#This Row],[PROV/AÑO]],COMPRAS!$C$4:$C$80,Tabla8[[#Headers],[2020]]) -> 0 | F35: =+SUMIFS(COMPRAS!$I$4:$I$80,COMPRAS!$E$4:$E$80,Tabla8[[#This Row],[PROV/AÑO]],COMPRAS!$C$4:$C$80,Tabla8[[#Headers],[2021]]) -> 0
A36: =B.D!F19 -> MATERIALES SU CONSTRUCCION S.A | B36: =+SUM(Tabla8[[#This Row],[2018]:[2021]]) -> 0 | C36: =+SUMIFS(COMPRAS!$I$4:$I$80,COMPRAS!$E$4:$E$80,Tabla8[[#This Row],[PROV/AÑO]],COMPRAS!$C$4:$C$80,Tabla8[[#Headers],[2018]]) -> 0 | D36: =+SUMIFS(COMPRAS!I19:I58,COMPRAS!E19:E58,Tabla8[[#This Row],[PROV/AÑO]],COMPRAS!C19:C58,Tabla8[[#Headers],[2019]]) -> 0 | E36: =+SUMIFS(COMPRAS!$I$4:$I$80,COMPRAS!$E$4:$E$80,Tabla8[[#This Row],[PROV/AÑO]],COMPRAS!$C$4:$C$80,Tabla8[[#Headers],[2020]]) -> 0 | F36: =+SUMIFS(COMPRAS!$I$4:$I$80,COMPRAS!$E$4:$E$80,Tabla8[[#This Row],[PROV/AÑO]],COMPRAS!$C$4:$C$80,Tabla8[[#Headers],[2021]]) -> 0
A37: =B.D!F10 -> PC CHAMPION S.A.S | B37: =+SUM(Tabla8[[#This Row],[2018]:[2021]]) -> 0 | C37: =+SUMIFS(COMPRAS!$I$4:$I$80,COMPRAS!$E$4:$E$80,Tabla8[[#This Row],[PROV/AÑO]],COMPRAS!$C$4:$C$80,Tabla8[[#Headers],[2018]]) -> 0 | D37: =+SUMIFS(COMPRAS!I10:I49,COMPRAS!E10:E49,Tabla8[[#This Row],[PROV/AÑO]],COMPRAS!C10:C49,Tabla8[[#Headers],[2019]]) -> 0 | E37: =+SUMIFS(COMPRAS!$I$4:$I$80,COMPRAS!$E$4:$E$80,Tabla8[[#This Row],[PROV/AÑO]],COMPRAS!$C$4:$C$80,Tabla8[[#Headers],[2020]]) -> 0 | F37: =+SUMIFS(COMPRAS!$I$4:$I$80,COMPRAS!$E$4:$E$80,Tabla8[[#This Row],[PROV/AÑO]],COMPRAS!$C$4:$C$80,Tabla8[[#Headers],[2021]]) -> 0
A38: =B.D!F27 -> PEDRO ANTONIO HERRERA | B38: =+SUM(Tabla8[[#This Row],[2018]:[2021]]) -> 0 | C38: =+SUMIFS(COMPRAS!$I$4:$I$80,COMPRAS!$E$4:$E$80,Tabla8[[#This Row],[PROV/AÑO]],COMPRAS!$C$4:$C$80,Tabla8[[#Headers],[2018]]) -> 0 | D38: =+SUMIFS(COMPRAS!I27:I103,COMPRAS!E27:E103,Tabla8[[#This Row],[PROV/AÑO]],COMPRAS!C27:C103,Tabla8[[#Headers],[2019]]) -> 0 | E38: =+SUMIFS(COMPRAS!$I$4:$I$80,COMPRAS!$E$4:$E$80,Tabla8[[#This Row],[PROV/AÑO]],COMPRAS!$C$4:$C$80,Tabla8[[#Headers],[2020]]) -> 0 | F38: =+SUMIFS(COMPRAS!$I$4:$I$80,COMPRAS!$E$4:$E$80,Tabla8[[#This Row],[PROV/AÑO]],COMPRAS!$C$4:$C$80,Tabla8[[#Headers],[2021]]) -> 0
A39: =B.D!F28 -> PLASTEXTIL S.A.S | B39: =+SUM(Tabla8[[#This Row],[2018]:[2021]]) -> 0 | C39: =+SUMIFS(COMPRAS!$I$4:$I$80,COMPRAS!$E$4:$E$80,Tabla8[[#This Row],[PROV/AÑO]],COMPRAS!$C$4:$C$80,Tabla8[[#Headers],[2018]]) -> 0 | D39: =+SUMIFS(COMPRAS!I28:I104,COMPRAS!E28:E104,Tabla8[[#This Row],[PROV/AÑO]],COMPRAS!C28:C104,Tabla8[[#Headers],[2019]]) -> 0 | E39: =+SUMIFS(COMPRAS!$I$4:$I$80,COMPRAS!$E$4:$E$80,Tabla8[[#This Row],[PROV/AÑO]],COMPRAS!$C$4:$C$80,Tabla8[[#Headers],[2020]]) -> 0 | F39: =+SUMIFS(COMPRAS!$I$4:$I$80,COMPRAS!$E$4:$E$80,Tabla8[[#This Row],[PROV/AÑO]],COMPRAS!$C$4:$C$80,Tabla8[[#Headers],[2021]]) -> 0
A40: =B.D!F7 -> PRODUCTOS COPLAST | B40: =+SUM(Tabla8[[#This Row],[2018]:[2021]]) -> 0 | C40: =+SUMIFS(COMPRAS!$I$4:$I$80,COMPRAS!$E$4:$E$80,Tabla8[[#This Row],[PROV/AÑO]],COMPRAS!$C$4:$C$80,Tabla8[[#Headers],[2018]]) -> 0 | D40: =+SUMIFS(COMPRAS!I7:I46,COMPRAS!E7:E46,Tabla8[[#This Row],[PROV/AÑO]],COMPRAS!C7:C46,Tabla8[[#Headers],[2019]]) -> 0 | E40: =+SUMIFS(COMPRAS!$I$4:$I$80,COMPRAS!$E$4:$E$80,Tabla8[[#This Row],[PROV/AÑO]],COMPRAS!$C$4:$C$80,Tabla8[[#Headers],[2020]]) -> 0 | F40: =+SUMIFS(COMPRAS!$I$4:$I$80,COMPRAS!$E$4:$E$80,Tabla8[[#This Row],[PROV/AÑO]],COMPRAS!$C$4:$C$80,Tabla8[[#Headers],[2021]]) -> 0
A41: =B.D!F16 -> PRODUCTOS COPLAST | B41: =+SUM(Tabla8[[#This Row],[2018]:[2021]]) -> 0 | C41: =+SUMIFS(COMPRAS!$I$4:$I$80,COMPRAS!$E$4:$E$80,Tabla8[[#This Row],[PROV/AÑO]],COMPRAS!$C$4:$C$80,Tabla8[[#Headers],[2018]]) -> 0 | D41: =+SUMIFS(COMPRAS!I16:I55,COMPRAS!E16:E55,Tabla8[[#This Row],[PROV/AÑO]],COMPRAS!C16:C55,Tabla8[[#Headers],[2019]]) -> 0 | E41: =+SUMIFS(COMPRAS!$I$4:$I$80,COMPRAS!$E$4:$E$80,Tabla8[[#This Row],[PROV/AÑO]],COMPRAS!$C$4:$C$80,Tabla8[[#Headers],[2020]]) -> 0 | F41: =+SUMIFS(COMPRAS!$I$4:$I$80,COMPRAS!$E$4:$E$80,Tabla8[[#This Row],[PROV/AÑO]],COMPRAS!$C$4:$C$80,Tabla8[[#Headers],[2021]]) -> 0
A42: =B.D!F31 -> RELOMAR S.A.S | B42: =+SUM(Tabla8[[#This Row],[2018]:[2021]]) -> 0 | C42: =+SUMIFS(COMPRAS!$I$4:$I$80,COMPRAS!$E$4:$E$80,Tabla8[[#This Row],[PROV/AÑO]],COMPRAS!$C$4:$C$80,Tabla8[[#Headers],[2018]]) -> 0 | D42: =+SUMIFS(COMPRAS!I31:I107,COMPRAS!E31:E107,Tabla8[[#This Row],[PROV/AÑO]],COMPRAS!C31:C107,Tabla8[[#Headers],[2019]]) -> 0 | E42: =+SUMIFS(COMPRAS!$I$4:$I$80,COMPRAS!$E$4:$E$80,Tabla8[[#This Row],[PROV/AÑO]],COMPRAS!$C$4:$C$80,Tabla8[[#Headers],[2020]]) -> 0 | F42: =+SUMIFS(COMPRAS!$I$4:$I$80,COMPRAS!$E$4:$E$80,Tabla8[[#This Row],[PROV/AÑO]],COMPRAS!$C$4:$C$80,Tabla8[[#Headers],[2021]]) -> 0
A43: =B.D!F41 -> SERVITECA LUBRIFILTROS BELLO S.A.S | B43: =+SUM(Tabla8[[#This Row],[2018]:[2021]]) -> 0 | C43: =+SUMIFS(COMPRAS!$I$4:$I$80,COMPRAS!$E$4:$E$80,Tabla8[[#This Row],[PROV/AÑO]],COMPRAS!$C$4:$C$80,Tabla8[[#Headers],[2018]]) -> 0 | D43: =+SUMIFS(COMPRAS!I41:I117,COMPRAS!E41:E117,Tabla8[[#This Row],[PROV/AÑO]],COMPRAS!C41:C117,Tabla8[[#Headers],[2019]]) -> 0 | E43: =+SUMIFS(COMPRAS!$I$4:$I$80,COMPRAS!$E$4:$E$80,Tabla8[[#This Row],[PROV/AÑO]],COMPRAS!$C$4:$C$80,Tabla8[[#Headers],[2020]]) -> 0 | F43: =+SUMIFS(COMPRAS!$I$4:$I$80,COMPRAS!$E$4:$E$80,Tabla8[[#This Row],[PROV/AÑO]],COMPRAS!$C$4:$C$80,Tabla8[[#Headers],[2021]]) -> 0
A44: =B.D!F15 -> SODIMAC COLOMBIA | B44: =+SUM(Tabla8[[#This Row],[2018]:[2021]]) -> 0 | C44: =+SUMIFS(COMPRAS!$I$4:$I$80,COMPRAS!$E$4:$E$80,Tabla8[[#This Row],[PROV/AÑO]],COMPRAS!$C$4:$C$80,Tabla8[[#Headers],[2018]]) -> 0 | D44: =+SUMIFS(COMPRAS!I15:I54,COMPRAS!E15:E54,Tabla8[[#This Row],[PROV/AÑO]],COMPRAS!C15:C54,Tabla8[[#Headers],[2019]]) -> 0 | E44: =+SUMIFS(COMPRAS!$I$4:$I$80,COMPRAS!$E$4:$E$80,Tabla8[[#This Row],[PROV/AÑO]],COMPRAS!$C$4:$C$80,Tabla8[[#Headers],[2020]]) -> 0 | F44: =+SUMIFS(COMPRAS!$I$4:$I$80,COMPRAS!$E$4:$E$80,Tabla8[[#This Row],[PROV/AÑO]],COMPRAS!$C$4:$C$80,Tabla8[[#Headers],[2021]]) -> 0
A45: =B.D!F24 -> SOFIA POSADA S.A.S | B45: =+SUM(Tabla8[[#This Row],[2018]:[2021]]) -> 0 | C45: =+SUMIFS(COMPRAS!$I$4:$I$80,COMPRAS!$E$4:$E$80,Tabla8[[#This Row],[PROV/AÑO]],COMPRAS!$C$4:$C$80,Tabla8[[#Headers],[2018]]) -> 0 | D45: =+SUMIFS(COMPRAS!I24:I63,COMPRAS!E24:E63,Tabla8[[#This Row],[PROV/AÑO]],COMPRAS!C24:C63,Tabla8[[#Headers],[2019]]) -> 0 | E45: =+SUMIFS(COMPRAS!$I$4:$I$80,COMPRAS!$E$4:$E$80,Tabla8[[#This Row],[PROV/AÑO]],COMPRAS!$C$4:$C$80,Tabla8[[#Headers],[2020]]) -> 0 | F45: =+SUMIFS(COMPRAS!$I$4:$I$80,COMPRAS!$E$4:$E$80,Tabla8[[#This Row],[PROV/AÑO]],COMPRAS!$C$4:$C$80,Tabla8[[#Headers],[2021]]) -> 0
A46: =B.D!F29 -> TODO TAPICERO S.A | B46: =+SUM(Tabla8[[#This Row],[2018]:[2021]]) -> 0 | C46: =+SUMIFS(COMPRAS!$I$4:$I$80,COMPRAS!$E$4:$E$80,Tabla8[[#This Row],[PROV/AÑO]],COMPRAS!$C$4:$C$80,Tabla8[[#Headers],[2018]]) -> 0 | D46: =+SUMIFS(COMPRAS!I29:I105,COMPRAS!E29:E105,Tabla8[[#This Row],[PROV/AÑO]],COMPRAS!C29:C105,Tabla8[[#Headers],[2019]]) -> 0 | E46: =+SUMIFS(COMPRAS!$I$4:$I$80,COMPRAS!$E$4:$E$80,Tabla8[[#This Row],[PROV/AÑO]],COMPRAS!$C$4:$C$80,Tabla8[[#Headers],[2020]]) -> 0 | F46: =+SUMIFS(COMPRAS!$I$4:$I$80,COMPRAS!$E$4:$E$80,Tabla8[[#This Row],[PROV/AÑO]],COMPRAS!$C$4:$C$80,Tabla8[[#Headers],[2021]]) -> 0
